src/verilog/constants.vh
`define ADDR_BUS_W 24
`define FE_ADDR_W 22
`define FE_DATA_W 32
`define BE_DATA_W 64
`define BE_ADDR_W 24
`define BE_STRB_W 8
`define FE_STRB_W 4
`define FIFO_DEPTH 16

src/verilog/accelerator_property.v
`include "constants.vh"

// Accelerator for Map/Reduce Operation (Counting Even Numbers)
module accelerator_property (
    input wire clk_i,
    input wire arst_i,
    input wire start,
    input wire [`FE_DATA_W-1:0] data_in,
    output reg [`FE_DATA_W-1:0] data_out,
    output reg done
);

    parameter NUM_WIDTH = `FE_DATA_W / 4; // Assuming 8 bits per number

    reg [31:0] count;
    reg [1:0] state;
    localparam IDLE = 2'b00;
    localparam DONE = 2'b01;

    // Extract four 8-bit numbers from 32-bit input
    wire [NUM_WIDTH-1:0] num0 = data_in[NUM_WIDTH-1:0];
    wire [NUM_WIDTH-1:0] num1 = data_in[2*NUM_WIDTH-1:NUM_WIDTH];
    wire [NUM_WIDTH-1:0] num2 = data_in[3*NUM_WIDTH-1:2*NUM_WIDTH];
    wire [NUM_WIDTH-1:0] num3 = data_in[4*NUM_WIDTH-1:3*NUM_WIDTH];

    // Condition: even numbers (lsb == 0)
    // To change condition, modify these lines, e.g., for numbers > 100: is_even0 = (num0 > 8'd100);
    wire is_even0 = ~num0[0];
    wire is_even1 = ~num1[0];
    wire is_even2 = ~num2[0];
    wire is_even3 = ~num3[0];

    wire [2:0] even_count = is_even0 + is_even1 + is_even2 + is_even3;

    always @(posedge clk_i or posedge arst_i) begin
        if (arst_i) begin
            count <= 32'h0;
            state <= IDLE;
            done <= 1'b0;
            data_out <= 32'h0;
        end else begin
            case (state)
                IDLE: begin
                    if (start) begin
                        count <= count + even_count;
                        data_out <= count + even_count;
                        state <= DONE;
                        done <= 1'b1;
                    end
                end
                DONE: begin
                    if (!start) begin
                        state <= IDLE;
                        done <= 1'b0;
                    end
                end
            endcase
        end
    end
endmodule

src/verilog/accelerator_count_tb.v
`include "constants.vh"
`timescale 1ns / 1ps

module accelerator_count_tb;

    parameter CLK_PERIOD = 10;
    parameter NUM_WIDTH = 8;

    reg clk_i;
    reg arst_i;
    reg start;
    reg [31:0] data_in;
    wire [31:0] data_out;
    wire done;
    reg [31:0] exp_count;
    reg [NUM_WIDTH-1:0] n0, n1, n2, n3;
    reg is_even0, is_even1, is_even2, is_even3;
    integer i;
    reg [31:0] data_sets [0:2];
    integer num_sets;
    reg [31:0] din;

    // DUT
    accelerator_property dut (
        .clk_i(clk_i),
        .arst_i(arst_i),
        .start(start),
        .data_in(data_in),
        .data_out(data_out),
        .done(done)
    );

    // Clock generation
    initial begin
        clk_i = 0;
        forever # (CLK_PERIOD / 2) clk_i = ~clk_i;
    end

    // Waveform dumping
    initial begin
        $dumpfile("wave_count.vcd");
        $dumpvars(0, accelerator_count_tb);
    end

    // Test procedure
    initial begin
        // Initialize
        arst_i = 1;
        start = 0;
        data_in = 0;
        #20 arst_i = 0;
        #(CLK_PERIOD);

        // Test case 1: Multiple sets
        begin
            exp_count = 0;
            data_sets[0] = 32'h01020304; // 1(odd),2(even),3(odd),4(even) -> 2 even
            data_sets[1] = 32'h05060708; // 5(odd),6(even),7(odd),8(even) -> 2 even
            data_sets[2] = 32'h090A0B0C; // 9(odd),10(even),11(odd),12(even) -> 2 even

            $display("Test case 1: Multiple sets");
            for (integer i = 0; i < 3; i++) begin
                n0 = data_sets[i][NUM_WIDTH-1:0];
                n1 = data_sets[i][2*NUM_WIDTH-1:NUM_WIDTH];
                n2 = data_sets[i][3*NUM_WIDTH-1:2*NUM_WIDTH];
                n3 = data_sets[i][4*NUM_WIDTH-1:3*NUM_WIDTH];

                is_even0 = ~n0[0];
                is_even1 = ~n1[0];
                is_even2 = ~n2[0];
                is_even3 = ~n3[0];

                exp_count = exp_count + is_even0 + is_even1 + is_even2 + is_even3;

                data_in = data_sets[i];
                start = 1;
                #(CLK_PERIOD);
                start = 0;
                wait(done == 1);
                #(CLK_PERIOD);
                if (data_out !== exp_count)
                    $display("Fail: set %d, expected count=%d, got %d", i, exp_count, data_out);
                else $display("Pass: set %d", i);
            end
        end

        // Test case 2: All even numbers
        begin
            arst_i = 1;
            #(CLK_PERIOD); arst_i = 0;
            #(CLK_PERIOD);

            exp_count = 0;
            data_in = 32'h02040608; // 2,4,6,8 -> all even

            exp_count = exp_count + 4; // All four are even

            $display("Test case 2: All even numbers");
            start = 1;
            #(CLK_PERIOD);
            start = 0;
            wait(done == 1);
            #(CLK_PERIOD);
            if (data_out !== exp_count)
                $display("Fail: expected count=4, got %d", data_out);
            else $display("Pass: all even");
        end

        // Test case 3: All odd numbers
        begin
            arst_i = 1;
            #(CLK_PERIOD); arst_i = 0;
            #(CLK_PERIOD);

            exp_count = 0;
            data_in = 32'h01030507; // 1,3,5,7 -> all odd

            exp_count = exp_count + 0; // None are even

            $display("Test case 3: All odd numbers");
            start = 1;
            #(CLK_PERIOD);
            start = 0;
            wait(done == 1);
            #(CLK_PERIOD);
            if (data_out !== exp_count)
                $display("Fail: expected count=0, got %d", data_out);
            else $display("Pass: all odd");
        end

        // Test case 4: Mid-operation reset
        begin
            arst_i = 1;
            #(CLK_PERIOD); arst_i = 0;
            #(CLK_PERIOD);

            exp_count = 0;

            $display("Test case 4: Mid-operation reset");
            // First set
            data_in = 32'h01020304; // 2 even
            start = 1;
            #(CLK_PERIOD);
            start = 0;

            exp_count = exp_count + 2;

            wait(done === 1);
            #(CLK_PERIOD);
            if (data_out !== 2)
                $display("Fail: after first set");
            else $display("Pass: first set");

            // Assert reset
            arst_i = 1;
            #(CLK_PERIOD);
            arst_i = 0;
            #(CLK_PERIOD);

            // Second set after reset
            exp_count = 0;
            data_in = 32'h05060708; // 2 even
            start = 1;
            #(CLK_PERIOD);
            start = 0;
            exp_count = exp_count + 2;

            wait(done === 1);
            #(CLK_PERIOD);
            if (data_out !== 2)
                $display("Fail: after reset and second set");
            else $display("Pass: after reset and second set");
        end

        // Test case 5: Large dataset
        begin
            arst_i = 1;
            #(CLK_PERIOD); arst_i = 0;
            #(CLK_PERIOD);

            exp_count = 0;
            num_sets = 1000;

            $display("Test case 5: Large dataset");
            for (integer i = 0; i < num_sets; i++) begin
                din = $random;
                data_in = din;

                n0 = din[NUM_WIDTH-1:0];
                n1 = din[2*NUM_WIDTH-1:NUM_WIDTH];
                n2 = din[3*NUM_WIDTH-1:2*NUM_WIDTH];
                n3 = din[4*NUM_WIDTH-1:3*NUM_WIDTH];

                is_even0 = ~n0[0];
                is_even1 = ~n1[0];
                is_even2 = ~n2[0];
                is_even3 = ~n3[0];

                exp_count = exp_count + is_even0 + is_even1 + is_even2 + is_even3;

                start = 1;
                #(CLK_PERIOD);
                start = 0;

                wait(done === 1);
                #(CLK_PERIOD);
                if (data_out !== exp_count)
                    $display("Fail: set %d, expected count=%d, got %d", i, exp_count, data_out);
                else if (i % 100 == 0) $display("Pass: set %d", i);
            end
            $display("Large dataset completed");
        end

        // Test case 6: Prolonged start signal
        begin
            arst_i = 1;
            #(CLK_PERIOD); arst_i = 0;
            #(CLK_PERIOD);

            exp_count = 0;
            data_in = 32'h01020304; // 2 even

            exp_count = exp_count + 2;

            $display("Test case 6: Prolonged start signal");
            start = 1;
            #(CLK_PERIOD);
            // Keep start high for extra cycles
            repeat (3) @(posedge clk_i);
            start = 0;


            wait(done === 1);
            #(CLK_PERIOD);
            if (data_out !== exp_count)
                $display("Fail: after prolonged start");
            else $display("Pass: prolonged start");
        end

        $display("All tests completed");
        $finish;
    end

endmodule

src/scripts/wave_count.vcd
$date
	Mon Jun 16 16:29:24 2025
$end
$version
	Icarus Verilog
$end
$timescale
	1ps
$end
$scope module accelerator_count_tb $end
$var wire 1 ! done $end
$var wire 32 " data_out [31:0] $end
$var parameter 32 # CLK_PERIOD $end
$var parameter 32 $ NUM_WIDTH $end
$var reg 1 % arst_i $end
$var reg 1 & clk_i $end
$var reg 32 ' data_in [31:0] $end
$var reg 32 ( din [31:0] $end
$var reg 32 ) exp_count [31:0] $end
$var reg 1 * is_even0 $end
$var reg 1 + is_even1 $end
$var reg 1 , is_even2 $end
$var reg 1 - is_even3 $end
$var reg 8 . n0 [7:0] $end
$var reg 8 / n1 [7:0] $end
$var reg 8 0 n2 [7:0] $end
$var reg 8 1 n3 [7:0] $end
$var reg 1 2 start $end
$var integer 32 3 num_sets [31:0] $end
$scope module dut $end
$var wire 1 % arst_i $end
$var wire 1 & clk_i $end
$var wire 32 4 data_in [31:0] $end
$var wire 1 5 is_even0 $end
$var wire 1 6 is_even1 $end
$var wire 1 7 is_even2 $end
$var wire 1 8 is_even3 $end
$var wire 1 2 start $end
$var wire 8 9 num3 [7:0] $end
$var wire 8 : num2 [7:0] $end
$var wire 8 ; num1 [7:0] $end
$var wire 8 < num0 [7:0] $end
$var wire 3 = even_count [2:0] $end
$var parameter 2 > DONE $end
$var parameter 2 ? IDLE $end
$var parameter 32 @ NUM_WIDTH $end
$var reg 32 A count [31:0] $end
$var reg 32 B data_out [31:0] $end
$var reg 1 ! done $end
$var reg 2 C state [1:0] $end
$upscope $end
$scope begin $ivl_for_loop0 $end
$var integer 32 D i [31:0] $end
$upscope $end
$scope begin $ivl_for_loop1 $end
$var integer 32 E i [31:0] $end
$upscope $end
$upscope $end
$enddefinitions $end
$comment Show the parameter values. $end
$dumpall
b1000 @
b0 ?
b1 >
b1000 $
b1010 #
$end
#0
$dumpvars
bx E
bx D
b0 C
b0 B
b0 A
b100 =
b0 <
b0 ;
b0 :
b0 9
18
17
16
15
b0 4
bx 3
02
bx 1
bx 0
bx /
bx .
x-
x,
x+
x*
bx )
bx (
b0 '
0&
1%
b0 "
0!
$end
#5000
1&
#10000
0&
#15000
1&
#20000
0&
0%
#25000
1&
#30000
06
b10 =
08
b100 <
b11 ;
b10 :
b1 9
0&
12
b1000000100000001100000100 '
b1000000100000001100000100 4
0-
1,
0+
1*
b1 1
b10 0
b11 /
b100 .
b0 D
b10 )
#35000
1!
b1 C
b10 "
b10 B
b10 A
1&
#40000
0&
02
#45000
0!
b0 C
1&
#50000
b1000 <
b111 ;
b110 :
b101 9
0&
12
b101000001100000011100001000 '
b101000001100000011100001000 4
b100 )
b101 1
b110 0
b111 /
b1000 .
b1 D
#55000
1!
b1 C
b100 "
b100 B
b100 A
1&
#60000
0&
02
#65000
0!
b0 C
1&
#70000
b1100 <
b1011 ;
b1010 :
b1001 9
0&
12
b1001000010100000101100001100 '
b1001000010100000101100001100 4
b110 )
b1001 1
b1010 0
b1011 /
b1100 .
b10 D
#75000
1!
b1 C
b110 "
b110 B
b110 A
1&
#80000
0&
02
#85000
0!
b0 C
1&
#90000
b0 "
b0 B
b0 A
0&
1%
b11 D
#95000
1&
#100000
0&
0%
#105000
1&
#110000
16
b100 =
18
b1000 <
b110 ;
b100 :
b10 9
0&
12
b10000001000000011000001000 '
b10000001000000011000001000 4
b100 )
#115000
1!
b1 C
b100 "
b100 B
b100 A
1&
#120000
0&
02
#125000
0!
b0 C
1&
#130000
b0 "
b0 B
b0 A
0&
1%
#135000
1&
#140000
0&
0%
#145000
1&
#150000
05
06
07
b0 =
08
b111 <
b101 ;
b11 :
b1 9
0&
12
b1000000110000010100000111 '
b1000000110000010100000111 4
b0 )
#155000
1!
b1 C
1&
#160000
0&
02
#165000
0!
b0 C
1&
#170000
0&
1%
#175000
1&
#180000
0&
0%
#185000
1&
#190000
15
b10 =
17
b100 <
b11 ;
b10 :
0&
12
b1000000100000001100000100 '
b1000000100000001100000100 4
#195000
1!
b1 C
b10 "
b10 B
b10 A
1&
#200000
0&
b10 )
02
#205000
0!
b0 C
1&
#210000
b0 "
b0 B
b0 A
0&
1%
#215000
1&
#220000
0&
0%
#225000
1&
#230000
b1000 <
b111 ;
b110 :
b101 9
0&
12
b101000001100000011100001000 '
b101000001100000011100001000 4
b0 )
#235000
1!
b1 C
b10 "
b10 B
b10 A
1&
#240000
0&
b10 )
02
#245000
0!
b0 C
1&
#250000
b0 "
b0 B
b0 A
0&
1%
#255000
1&
#260000
0&
0%
#265000
1&
#270000
07
b10 =
18
b100100 <
b110101 ;
b10101 :
b10010 9
0&
12
1-
0,
b10010 1
b10101 0
b110101 /
b100100 .
b10010000101010011010100100100 '
b10010000101010011010100100100 4
b10010000101010011010100100100 (
b0 E
b1111101000 3
b10 )
#275000
1!
b1 C
b10 "
b10 B
b10 A
1&
#280000
0&
02
#285000
0!
b0 C
1&
#290000
05
b10 =
16
b10000001 <
b1011110 ;
b10001001 :
b11000000 9
0&
12
b100 )
1+
0*
b11000000 1
b10001001 0
b1011110 /
b10000001 .
b11000000100010010101111010000001 '
b11000000100010010101111010000001 4
b11000000100010010101111010000001 (
b1 E
#295000
1!
b1 C
b100 "
b100 B
b100 A
1&
#300000
0&
02
#305000
0!
b0 C
1&
#310000
b11 =
17
b1001 <
b11010110 ;
b10000100 :
b10000100 9
0&
12
b111 )
1,
b10000100 1
b10000100 0
b11010110 /
b1001 .
b10000100100001001101011000001001 '
b10000100100001001101011000001001 4
b10000100100001001101011000001001 (
b10 E
#315000
1!
b1 C
b111 "
b111 B
b111 A
1&
#320000
0&
02
#325000
0!
b0 C
1&
#330000
b10 =
08
b1100011 <
b1010110 ;
b11110000 :
b10110001 9
0&
12
b1001 )
0-
b10110001 1
b11110000 0
b1010110 /
b1100011 .
b10110001111100000101011001100011 '
b10110001111100000101011001100011 4
b10110001111100000101011001100011 (
b11 E
#335000
1!
b1 C
b1001 "
b1001 B
b1001 A
1&
#340000
0&
02
#345000
0!
b0 C
1&
#350000
06
07
b1 =
18
b1101 <
b1111011 ;
b10111001 :
b110 9
0&
12
b1010 )
1-
0,
0+
b110 1
b10111001 0
b1111011 /
b1101 .
b110101110010111101100001101 '
b110101110010111101100001101 4
b110101110010111101100001101 (
b100 E
#355000
1!
b1 C
b1010 "
b1010 B
b1010 A
1&
#360000
0&
02
#365000
0!
b0 C
1&
#370000
b10001101 <
b10011001 ;
b11011111 :
b1000110 9
0&
12
b1011 )
b1000110 1
b11011111 0
b10011001 /
b10001101 .
b1000110110111111001100110001101 '
b1000110110111111001100110001101 4
b1000110110111111001100110001101 (
b101 E
#375000
1!
b1 C
b1011 "
b1011 B
b1011 A
1&
#380000
0&
02
#385000
0!
b0 C
1&
#390000
16
b11 =
17
b1100101 <
b10000100 ;
b11000010 :
b10110010 9
0&
12
b1110 )
1,
1+
b10110010 1
b11000010 0
b10000100 /
b1100101 .
b10110010110000101000010001100101 '
b10110010110000101000010001100101 4
b10110010110000101000010001100101 (
b110 E
#395000
1!
b1 C
b1110 "
b1110 B
b1110 A
1&
#400000
0&
02
#405000
0!
b0 C
1&
#410000
15
07
b10 =
08
b10010 <
b1010010 ;
b110111 :
b10001001 9
0&
12
b10000 )
0-
0,
1*
b10001001 1
b110111 0
b1010010 /
b10010 .
b10001001001101110101001000010010 '
b10001001001101110101001000010010 4
b10001001001101110101001000010010 (
b111 E
#415000
1!
b1 C
b10000 "
b10000 B
b10000 A
1&
#420000
0&
02
#425000
0!
b0 C
1&
#430000
05
06
b1 =
18
b1 <
b11100011 ;
b11110011 :
b0 9
0&
12
b10001 )
1-
0+
0*
b0 1
b11110011 0
b11100011 /
b1 .
b111100111110001100000001 '
b111100111110001100000001 4
b111100111110001100000001 (
b1000 E
#435000
1!
b1 C
b10001 "
b10001 B
b10001 A
1&
#440000
0&
02
#445000
0!
b0 C
1&
#450000
b1101 <
b11001101 ;
b11010111 :
b110 9
0&
12
b10010 )
b110 1
b11010111 0
b11001101 /
b1101 .
b110110101111100110100001101 '
b110110101111100110100001101 4
b110110101111100110100001101 (
b1001 E
#455000
1!
b1 C
b10010 "
b10010 B
b10010 A
1&
#460000
0&
02
#465000
0!
b0 C
1&
#470000
15
b1 =
08
b1110110 <
b11110001 ;
b100011 :
b111011 9
0&
12
b10011 )
0-
1*
b111011 1
b100011 0
b11110001 /
b1110110 .
b111011001000111111000101110110 '
b111011001000111111000101110110 4
b111011001000111111000101110110 (
b1010 E
#475000
1!
b1 C
b10011 "
b10011 B
b10011 A
1&
#480000
0&
02
#485000
0!
b0 C
1&
#490000
05
b1 =
18
b111101 <
b11001101 ;
b10001101 :
b11110 9
0&
12
b10100 )
1-
0*
b11110 1
b10001101 0
b11001101 /
b111101 .
b11110100011011100110100111101 '
b11110100011011100110100111101 4
b11110100011011100110100111101 (
b1011 E
#495000
1!
b1 C
b10100 "
b10100 B
b10100 A
1&
#500000
0&
02
#505000
0!
b0 C
1&
#510000
b10 =
17
b11101101 <
b1010111 ;
b11010100 :
b1110110 9
0&
12
b10110 )
1,
b1110110 1
b11010100 0
b1010111 /
b11101101 .
b1110110110101000101011111101101 '
b1110110110101000101011111101101 4
b1110110110101000101011111101101 (
b1100 E
#515000
1!
b1 C
b10110 "
b10110 B
b10110 A
1&
#520000
0&
02
#525000
0!
b0 C
1&
#530000
15
b10 =
07
b10001100 <
b11110111 ;
b101101 :
b1000110 9
0&
12
b11000 )
0,
1*
b1000110 1
b101101 0
b11110111 /
b10001100 .
b1000110001011011111011110001100 '
b1000110001011011111011110001100 4
b1000110001011011111011110001100 (
b1101 E
#535000
1!
b1 C
b11000 "
b11000 B
b11000 A
1&
#540000
0&
02
#545000
0!
b0 C
1&
#550000
b1 =
05
b11111001 <
b11101001 ;
b11111101 :
b1111100 9
0&
12
b11001 )
0*
b1111100 1
b11111101 0
b11101001 /
b11111001 .
b1111100111111011110100111111001 '
b1111100111111011110100111111001 4
b1111100111111011110100111111001 (
b1110 E
#555000
1!
b1 C
b11001 "
b11001 B
b11001 A
1&
#560000
0&
02
#565000
0!
b0 C
1&
#570000
15
16
b10 =
08
b11000110 <
b100100 ;
b110111 :
b11100011 9
0&
12
b11011 )
0-
1+
1*
b11100011 1
b110111 0
b100100 /
b11000110 .
b11100011001101110010010011000110 '
b11100011001101110010010011000110 4
b11100011001101110010010011000110 (
b1111 E
#575000
1!
b1 C
b11011 "
b11011 B
b11011 A
1&
#580000
0&
02
#585000
0!
b0 C
1&
#590000
05
b10 =
18
b11000101 <
b10000100 ;
b11110111 :
b11100010 9
0&
12
b11101 )
1-
0*
b11100010 1
b11110111 0
b10000100 /
b11000101 .
b11100010111101111000010011000101 '
b11100010111101111000010011000101 4
b11100010111101111000010011000101 (
b10000 E
#595000
1!
b1 C
b11101 "
b11101 B
b11101 A
1&
#600000
0&
02
#605000
0!
b0 C
1&
#610000
15
b10 =
08
b10101010 <
b11010010 ;
b10011 :
b11010101 9
0&
12
b11111 )
0-
1*
b11010101 1
b10011 0
b11010010 /
b10101010 .
b11010101000100111101001010101010 '
b11010101000100111101001010101010 4
b11010101000100111101001010101010 (
b10001 E
#615000
1!
b1 C
b11111 "
b11111 B
b11111 A
1&
#620000
0&
02
#625000
0!
b0 C
1&
#630000
05
06
b1 =
18
b11100101 <
b11110111 ;
b10101111 :
b1110010 9
0&
12
b100000 )
1-
0+
0*
b1110010 1
b10101111 0
b11110111 /
b11100101 .
b1110010101011111111011111100101 '
b1110010101011111111011111100101 4
b1110010101011111111011111100101 (
b10010 E
#635000
1!
b1 C
b100000 "
b100000 B
b100000 A
1&
#640000
0&
02
#645000
0!
b0 C
1&
#650000
16
17
b10 =
08
b1110111 <
b1110010 ;
b11010010 :
b10111011 9
0&
12
b100010 )
0-
1,
1+
b10111011 1
b11010010 0
b1110010 /
b1110111 .
b10111011110100100111001001110111 '
b10111011110100100111001001110111 4
b10111011110100100111001001110111 (
b10011 E
#655000
1!
b1 C
b100010 "
b100010 B
b100010 A
1&
#660000
0&
02
#665000
0!
b0 C
1&
#670000
b11 =
15
b10010 <
b11010110 ;
b110010 :
b10001001 9
0&
12
b100101 )
1*
b10001001 1
b110010 0
b11010110 /
b10010 .
b10001001001100101101011000010010 '
b10001001001100101101011000010010 4
b10001001001100101101011000010010 (
b10100 E
#675000
1!
b1 C
b100101 "
b100101 B
b100101 A
1&
#680000
0&
02
#685000
0!
b0 C
1&
#690000
05
b1 =
06
b10001111 <
b11011011 ;
b11101100 :
b1000111 9
0&
12
b100110 )
0+
0*
b1000111 1
b11101100 0
b11011011 /
b10001111 .
b1000111111011001101101110001111 '
b1000111111011001101101110001111 4
b1000111111011001101101110001111 (
b10101 E
#695000
1!
b1 C
b100110 "
b100110 B
b100110 A
1&
#700000
0&
02
#705000
0!
b0 C
1&
#710000
b10 =
15
b11110010 <
b1101001 ;
b110000 :
b1111001 9
0&
12
b101000 )
1*
b1111001 1
b110000 0
b1101001 /
b11110010 .
b1111001001100000110100111110010 '
b1111001001100000110100111110010 4
b1111001001100000110100111110010 (
b10110 E
#715000
1!
b1 C
b101000 "
b101000 B
b101000 A
1&
#720000
0&
02
#725000
0!
b0 C
1&
#730000
b11 =
16
b11001110 <
b10010110 ;
b1110110 :
b11100111 9
0&
12
b101011 )
1+
b11100111 1
b1110110 0
b10010110 /
b11001110 .
b11100111011101101001011011001110 '
b11100111011101101001011011001110 4
b11100111011101101001011011001110 (
b10111 E
#735000
1!
b1 C
b101011 "
b101011 B
b101011 A
1&
#740000
0&
02
#745000
0!
b0 C
1&
#750000
b100 =
18
b11101000 <
b1111010 ;
b0 :
b11110100 9
0&
12
b101111 )
1-
b11110100 1
b0 0
b1111010 /
b11101000 .
b11110100000000000111101011101000 '
b11110100000000000111101011101000 4
b11110100000000000111101011101000 (
b11000 E
#755000
1!
b1 C
b101111 "
b101111 B
b101111 A
1&
#760000
0&
02
#765000
0!
b0 C
1&
#770000
b11 =
05
b11000101 <
b1001110 ;
b11001010 :
b11100010 9
0&
12
b110010 )
0*
b11100010 1
b11001010 0
b1001110 /
b11000101 .
b11100010110010100100111011000101 '
b11100010110010100100111011000101 4
b11100010110010100100111011000101 (
b11001 E
#775000
1!
b1 C
b110010 "
b110010 B
b110010 A
1&
#780000
0&
02
#785000
0!
b0 C
1&
#790000
15
b11 =
06
b1011100 <
b1001001 ;
b1011000 :
b101110 9
0&
12
b110101 )
0+
1*
b101110 1
b1011000 0
b1001001 /
b1011100 .
b101110010110000100100101011100 '
b101110010110000100100101011100 4
b101110010110000100100101011100 (
b11010 E
#795000
1!
b1 C
b110101 "
b110101 B
b110101 A
1&
#800000
0&
02
#805000
0!
b0 C
1&
#810000
05
b11 =
16
b10111101 <
b101000 ;
b10001110 :
b11011110 9
0&
12
b111000 )
1+
0*
b11011110 1
b10001110 0
b101000 /
b10111101 .
b11011110100011100010100010111101 '
b11011110100011100010100010111101 4
b11011110100011100010100010111101 (
b11011 E
#815000
1!
b1 C
b111000 "
b111000 B
b111000 A
1&
#820000
0&
02
#825000
0!
b0 C
1&
#830000
b10 =
07
b101101 <
b1011000 ;
b10101011 :
b10010110 9
0&
12
b111010 )
0,
b10010110 1
b10101011 0
b1011000 /
b101101 .
b10010110101010110101100000101101 '
b10010110101010110101100000101101 4
b10010110101010110101100000101101 (
b11100 E
#835000
1!
b1 C
b111010 "
b111010 B
b111010 A
1&
#840000
0&
02
#845000
0!
b0 C
1&
#850000
b1100101 <
b100110 ;
b10100111 :
b10110010 9
0&
12
b111100 )
b10110010 1
b10100111 0
b100110 /
b1100101 .
b10110010101001110010011001100101 '
b10110010101001110010011001100101 4
b10110010101001110010011001100101 (
b11101 E
#855000
1!
b1 C
b111100 "
b111100 B
b111100 A
1&
#860000
0&
02
#865000
0!
b0 C
1&
#870000
b1 =
08
b1100011 <
b1100010 ;
b11101111 :
b10110001 9
0&
12
b111101 )
0-
b10110001 1
b11101111 0
b1100010 /
b1100011 .
b10110001111011110110001001100011 '
b10110001111011110110001001100011 4
b10110001111011110110001001100011 (
b11110 E
#875000
1!
b1 C
b111101 "
b111101 B
b111101 A
1&
#880000
0&
02
#885000
0!
b0 C
1&
#890000
15
b1 =
06
b1010 <
b10000111 ;
b1110011 :
b101 9
0&
12
b111110 )
0+
1*
b101 1
b1110011 0
b10000111 /
b1010 .
b101011100111000011100001010 '
b101011100111000011100001010 4
b101011100111000011100001010 (
b11111 E
#895000
1!
b1 C
b111110 "
b111110 B
b111110 A
1&
#900000
0&
02
#905000
0!
b0 C
1&
#910000
16
b11 =
18
b10000000 <
b100010 ;
b111011 :
b11000000 9
0&
12
b1000001 )
1-
1+
b11000000 1
b111011 0
b100010 /
b10000000 .
b11000000001110110010001010000000 '
b11000000001110110010001010000000 4
b11000000001110110010001010000000 (
b100000 E
#915000
1!
b1 C
b1000001 "
b1000001 B
b1000001 A
1&
#920000
0&
02
#925000
0!
b0 C
1&
#930000
06
b11 =
17
b100000 <
b100001 ;
b1100100 :
b10000 9
0&
12
b1000100 )
1,
0+
b10000 1
b1100100 0
b100001 /
b100000 .
b10000011001000010000100100000 '
b10000011001000010000100100000 4
b10000011001000010000100100000 (
b100001 E
#935000
1!
b1 C
b1000100 "
b1000100 B
b1000100 A
1&
#940000
0&
02
#945000
0!
b0 C
1&
#950000
b10 =
08
b10101010 <
b1000101 ;
b1111000 :
b1010101 9
0&
12
b1000110 )
0-
b1010101 1
b1111000 0
b1000101 /
b10101010 .
b1010101011110000100010110101010 '
b1010101011110000100010110101010 4
b1010101011110000100010110101010 (
b100010 E
#955000
1!
b1 C
b1000110 "
b1000110 B
b1000110 A
1&
#960000
0&
02
#965000
0!
b0 C
1&
#970000
05
16
b11 =
18
b10011101 <
b11001100 ;
b11001100 :
b11001110 9
0&
12
b1001001 )
1-
1+
0*
b11001110 1
b11001100 0
b11001100 /
b10011101 .
b11001110110011001100110010011101 '
b11001110110011001100110010011101 4
b11001110110011001100110010011101 (
b100011 E
#975000
1!
b1 C
b1001001 "
b1001001 B
b1001001 A
1&
#980000
0&
02
#985000
0!
b0 C
1&
#990000
15
b11 =
08
b10010110 <
b111110 ;
b100000 :
b11001011 9
0&
12
b1001100 )
0-
1*
b11001011 1
b100000 0
b111110 /
b10010110 .
b11001011001000000011111010010110 '
b11001011001000000011111010010110 4
b11001011001000000011111010010110 (
b100100 E
#995000
1!
b1 C
b1001100 "
b1001100 B
b1001100 A
1&
#1000000
0&
02
#1005000
0!
b0 C
1&
#1010000
05
b1 =
07
b10011 <
b10111000 ;
b10000011 :
b10001001 9
0&
12
b1001101 )
0,
0*
b10001001 1
b10000011 0
b10111000 /
b10011 .
b10001001100000111011100000010011 '
b10001001100000111011100000010011 4
b10001001100000111011100000010011 (
b100101 E
#1015000
1!
b1 C
b1001101 "
b1001101 B
b1001101 A
1&
#1020000
0&
02
#1025000
0!
b0 C
1&
#1030000
17
b11 =
18
b1101 <
b111000 ;
b10111100 :
b10000110 9
0&
12
b1010000 )
1-
1,
b10000110 1
b10111100 0
b111000 /
b1101 .
b10000110101111000011100000001101 '
b10000110101111000011100000001101 4
b10000110101111000011100000001101 (
b100110 E
#1035000
1!
b1 C
b1010000 "
b1010000 B
b1010000 A
1&
#1040000
0&
02
#1045000
0!
b0 C
1&
#1050000
07
b1 =
08
b1010011 <
b11010110 ;
b10100111 :
b10101001 9
0&
12
b1010001 )
0-
0,
b10101001 1
b10100111 0
b11010110 /
b1010011 .
b10101001101001111101011001010011 '
b10101001101001111101011001010011 4
b10101001101001111101011001010011 (
b100111 E
#1055000
1!
b1 C
b1010001 "
b1010001 B
b1010001 A
1&
#1060000
0&
02
#1065000
0!
b0 C
1&
#1070000
b0 =
06
b1101011 <
b11011101 ;
b10011111 :
b110101 9
0&
12
0+
b110101 1
b10011111 0
b11011101 /
b1101011 .
b110101100111111101110101101011 '
b110101100111111101110101101011 4
b110101100111111101110101101011 (
b101000 E
#1075000
1!
b1 C
1&
#1080000
0&
02
#1085000
0!
b0 C
1&
#1090000
16
17
b11 =
18
b11010101 <
b101010 ;
b10100110 :
b11101010 9
0&
12
b1010100 )
1-
1,
1+
b11101010 1
b10100110 0
b101010 /
b11010101 .
b11101010101001100010101011010101 '
b11101010101001100010101011010101 4
b11101010101001100010101011010101 (
b101001 E
#1095000
1!
b1 C
b1010100 "
b1010100 B
b1010100 A
1&
#1100000
0&
02
#1105000
0!
b0 C
1&
#1110000
15
07
b10 =
08
b10 <
b1001010 ;
b10111 :
b10000001 9
0&
12
b1010110 )
0-
0,
1*
b10000001 1
b10111 0
b1001010 /
b10 .
b10000001000101110100101000000010 '
b10000001000101110100101000000010 4
b10000001000101110100101000000010 (
b101010 E
#1115000
1!
b1 C
b1010110 "
b1010110 B
b1010110 A
1&
#1120000
0&
02
#1125000
0!
b0 C
1&
#1130000
b11 =
17
b10101110 <
b111110 ;
b1010110 :
b11010111 9
0&
12
b1011001 )
1,
b11010111 1
b1010110 0
b111110 /
b10101110 .
b11010111010101100011111010101110 '
b11010111010101100011111010101110 4
b11010111010101100011111010101110 (
b101011 E
#1135000
1!
b1 C
b1011001 "
b1011001 B
b1011001 A
1&
#1140000
0&
02
#1145000
0!
b0 C
1&
#1150000
05
06
07
b1 =
18
b11101 <
b11101001 ;
b11111111 :
b1110 9
0&
12
b1011010 )
1-
0,
0+
0*
b1110 1
b11111111 0
b11101001 /
b11101 .
b1110111111111110100100011101 '
b1110111111111110100100011101 4
b1110111111111110100100011101 (
b101100 E
#1155000
1!
b1 C
b1011010 "
b1011010 B
b1011010 A
1&
#1160000
0&
02
#1165000
0!
b0 C
1&
#1170000
16
b1 =
08
b11001111 <
b1110010 ;
b11000101 :
b11100111 9
0&
12
b1011011 )
0-
1+
b11100111 1
b11000101 0
b1110010 /
b11001111 .
b11100111110001010111001011001111 '
b11100111110001010111001011001111 4
b11100111110001010111001011001111 (
b101101 E
#1175000
1!
b1 C
b1011011 "
b1011011 B
b1011011 A
1&
#1180000
0&
02
#1185000
0!
b0 C
1&
