src/verilog/constants.vh
`define ADDR_BUS_W 24
`define FE_ADDR_W 22
`define FE_DATA_W 32
`define BE_DATA_W 64
`define BE_ADDR_W 24
`define BE_STRB_W 8
`define FE_STRB_W 4
`define FIFO_DEPTH 16

src/verilog/accelerator_max_min.v
`include "constants.vh"

// Accelerator for Maximum and Minimum Calculation
module accelerator_max_min (
    input wire clk_i,
    input wire arst_i,
    input wire start,
    input wire [`FE_DATA_W-1:0] data_in,
    output reg [`FE_DATA_W-1:0] data_out,
    output reg done
);

    parameter NUM_WIDTH = `FE_DATA_W / 4; // Assuming 8 bits per number

    reg [NUM_WIDTH-1:0] current_max;
    reg [NUM_WIDTH-1:0] current_min;
    reg [1:0] state;
    localparam IDLE = 2'b00;
    localparam DONE = 2'b01;

    // Extract four 8-bit numbers from 32-bit input
    wire [NUM_WIDTH-1:0] num0 = data_in[NUM_WIDTH-1:0];
    wire [NUM_WIDTH-1:0] num1 = data_in[2*NUM_WIDTH-1:NUM_WIDTH];
    wire [NUM_WIDTH-1:0] num2 = data_in[3*NUM_WIDTH-1:2*NUM_WIDTH];
    wire [NUM_WIDTH-1:0] num3 = data_in[4*NUM_WIDTH-1:3*NUM_WIDTH];

    // Compute maximum of the four numbers
    wire [NUM_WIDTH-1:0] max_temp1 = (num0 > num1) ? num0 : num1;
    wire [NUM_WIDTH-1:0] max_temp2 = (num2 > num3) ? num2 : num3;
    wire [NUM_WIDTH-1:0] max_of_four = (max_temp1 > max_temp2) ? max_temp1 : max_temp2;

    // Compute minimum of the four numbers
    wire [NUM_WIDTH-1:0] min_temp1 = (num0 < num1) ? num0 : num1;
    wire [NUM_WIDTH-1:0] min_temp2 = (num2 < num3) ? num2 : num3;
    wire [NUM_WIDTH-1:0] min_of_four = (min_temp1 < min_temp2) ? min_temp1 : min_temp2;

    // Determine new maximum and minimum
    wire [NUM_WIDTH-1:0] new_max = (max_of_four > current_max) ? max_of_four : current_max;
    wire [NUM_WIDTH-1:0] new_min = (min_of_four < current_min) ? min_of_four : current_min;

    always @(posedge clk_i or posedge arst_i) begin
        if (arst_i) begin
            current_max <= {NUM_WIDTH{1'b0}}; // Initialize to 0
            current_min <= {NUM_WIDTH{1'b1}}; // Initialize to 255
            state <= IDLE;
            done <= 1'b0;
            data_out <= {`FE_DATA_W{1'b0}};
        end else begin
            case (state)
                IDLE: begin
                    if (start) begin
                        current_max <= new_max;
                        current_min <= new_min;
                        data_out <= { {(`FE_DATA_W - 2*NUM_WIDTH){1'b0}}, new_max, new_min }; // [15:8]=max, [7:0]=min
                        state <= DONE;
                        done <= 1'b1;
                    end
                end
                DONE: begin
                    if (!start) begin
                        state <= IDLE;
                        done <= 1'b0;
                    end
                end
            endcase
        end
    end
endmodule

src/verilog/accelerator_max_min_tb.v
`include "constants.vh"
`timescale 1ns / 1ps

module accelerator_max_min_tb;

    parameter CLK_PERIOD = 10;
    parameter NUM_WIDTH = 8;

    reg clk_i;
    reg arst_i;
    reg start;
    reg [31:0] data_sets [0:2];
    reg [NUM_WIDTH-1:0] exp_max, exp_min;
    reg [NUM_WIDTH-1:0] n0, n1, n2, n3;
    reg [NUM_WIDTH-1:0] temp_max, temp_min;
    reg [NUM_WIDTH-1:0] new_exp_max, new_exp_min;
    reg [31:0] data_in_local;
    integer num_sets;
    reg [31:0] data_in;
    wire [31:0] data_out;
    wire done;

    // DUT
    accelerator_max_min dut (
        .clk_i(clk_i),
        .arst_i(arst_i),
        .start(start),
        .data_in(data_in),
        .data_out(data_out),
        .done(done)
    );

    // Clock generation
    initial begin
        clk_i = 0;
        forever # (CLK_PERIOD / 2) clk_i = ~clk_i;
    end

    // Waveform dumping
    initial begin
        $dumpfile("wave_max_min.vcd");
        $dumpvars(0, accelerator_max_min_tb);
    end

    // Functions
    function [NUM_WIDTH-1:0] max_of_four;
        input [NUM_WIDTH-1:0] a, b, c, d;
        begin
            max_of_four = (a > b) ? a : b;
            max_of_four = (max_of_four > c) ? max_of_four : c;
            max_of_four = (max_of_four > d) ? max_of_four : d;
        end
    endfunction

    function [NUM_WIDTH-1:0] min_of_four;
        input [NUM_WIDTH-1:0] a, b, c, d;
        begin
            min_of_four = (a < b) ? a : b;
            min_of_four = (min_of_four < c) ? min_of_four : c;
            min_of_four = (min_of_four < d) ? min_of_four : d;
        end
    endfunction

    // Test procedure
    initial begin
        // Initialize
        data_in = 0;
        start = 0;
        arst_i = 1;
        #20;
        arst_i = 0;
        #(CLK_PERIOD);

        // Test case 1: Multiple sets
        $display("Test case 1: Multiple sets");
        data_sets[0] = 32'h01020304;
        data_sets[1] = 32'h05060708;
        data_sets[2] = 32'h090A0B0C;
        exp_max = 0;
        exp_min = {NUM_WIDTH{1'b1}};
        for (integer i = 0; i < 3; i = i + 1) begin
            data_in_local = data_sets[i];
            n0 = data_in_local[7:0];
            n1 = data_in_local[15:8];
            n2 = data_in_local[23:16];
            n3 = data_in_local[31:24];
            temp_max = max_of_four(n0, n1, n2, n3);
            temp_min = min_of_four(n0, n1, n2, n3);
            new_exp_max = (exp_max > temp_max) ? exp_max : temp_max;
            new_exp_min = (exp_min < temp_min) ? exp_min : temp_min;
            data_in = data_in_local;
            start = 1;
            #(CLK_PERIOD);
            start = 0;
            wait(done == 1);
            #(CLK_PERIOD);
            if (data_out[15:8] !== new_exp_max || data_out[7:0] !== new_exp_min)
                $display("Fail: set %d, expected max=%d, min=%d, got max=%d, min=%d", i, new_exp_max, new_exp_min, data_out[15:8], data_out[7:0]);
            else $display("Pass: set %d", i);
            exp_max = new_exp_max;
            exp_min = new_exp_min;
        end

        // Test case 2: All zeros
        $display("Test case 2: All zeros");
        arst_i = 1;
        #(CLK_PERIOD);
        arst_i = 0;
        #(CLK_PERIOD);
        exp_max = 0;
        exp_min = {NUM_WIDTH{1'b1}};
        data_in_local = 32'h00000000;
        n0 = data_in_local[7:0];
        n1 = data_in_local[15:8];
        n2 = data_in_local[23:16];
        n3 = data_in_local[31:24];
        temp_max = max_of_four(n0, n1, n2, n3);
        temp_min = min_of_four(n0, n1, n2, n3);
        new_exp_max = (exp_max > temp_max) ? exp_max : temp_max;
        new_exp_min = (exp_min < temp_min) ? exp_min : temp_min;
        data_in = data_in_local;
        start = 1;
        #(CLK_PERIOD);
        start = 0;
        wait(done == 1);
        #(CLK_PERIOD);
        if (data_out[15:8] !== new_exp_max || data_out[7:0] !== new_exp_min)
            $display("Fail: all zeros, expected max=0, min=0, got max=%d, min=%d", data_out[15:8], data_out[7:0]);
        else $display("Pass: all zeros");

        // Test case 3: All maximum values (255)
        $display("Test case 3: All 255");
        arst_i = 1;
        #(CLK_PERIOD);
        arst_i = 0;
        #(CLK_PERIOD);
        exp_max = 0;
        exp_min = {NUM_WIDTH{1'b1}};
        data_in_local = 32'hFFFFFFFF;
        n0 = data_in_local[7:0];
        n1 = data_in_local[15:8];
        n2 = data_in_local[23:16];
        n3 = data_in_local[31:24];
        temp_max = max_of_four(n0, n1, n2, n3);
        temp_min = min_of_four(n0, n1, n2, n3);
        new_exp_max = (exp_max > temp_max) ? exp_max : temp_max;
        new_exp_min = (exp_min < temp_min) ? exp_min : temp_min;
        data_in = data_in_local;
        start = 1;
        #(CLK_PERIOD);
        start = 0;
        wait(done == 1);
        #(CLK_PERIOD);
        if (data_out[15:8] !== 255 || data_out[7:0] !== 255)
            $display("Fail: all 255, expected max=255, min=255, got max=%d, min=%d", data_out[15:8], data_out[7:0]);
        else $display("Pass: all 255");

        // Test case 4: Mid-operation reset
        $display("Test case 4: Mid-operation reset");
        arst_i = 1;
        #(CLK_PERIOD);
        arst_i = 0;
        #(CLK_PERIOD);
        exp_max = 0;
        exp_min = {NUM_WIDTH{1'b1}};
        // First set
        data_in_local = 32'h01020304;
        n0 = data_in_local[7:0];
        n1 = data_in_local[15:8];
        n2 = data_in_local[23:16];
        n3 = data_in_local[31:24];
        temp_max = max_of_four(n0, n1, n2, n3);
        temp_min = min_of_four(n0, n1, n2, n3);
        new_exp_max = (exp_max > temp_max) ? exp_max : temp_max;
        new_exp_min = (exp_min < temp_min) ? exp_min : temp_min;
        data_in = data_in_local;
        start = 1;
        #(CLK_PERIOD);
        start = 0;
        wait(done == 1);
        #(CLK_PERIOD);
        if (data_out[15:8] !== new_exp_max || data_out[7:0] !== new_exp_min)
            $display("Fail: after first set");
        else $display("Pass: first set");
        // Assert reset
        arst_i = 1;
        #(CLK_PERIOD);
        arst_i = 0;
        #(CLK_PERIOD);
        // Second set after reset
        exp_max = 0;
        exp_min = {NUM_WIDTH{1'b1}};
        data_in_local = 32'h05060708;
        n0 = data_in_local[7:0];
        n1 = data_in_local[15:8];
        n2 = data_in_local[23:16];
        n3 = data_in_local[31:24];
        temp_max = max_of_four(n0, n1, n2, n3);
        temp_min = min_of_four(n0, n1, n2, n3);
        new_exp_max = (exp_max > temp_max) ? exp_max : temp_max;
        new_exp_min = (exp_min < temp_min) ? exp_min : temp_min;
        data_in = data_in_local;
        start = 1;
        #(CLK_PERIOD);
        start = 0;
        wait(done == 1);
        #(CLK_PERIOD);
        if (data_out[15:8] !== new_exp_max || data_out[7:0] !== new_exp_min)
            $display("Fail: after reset and second set");
        else $display("Pass: after reset and second set");

        // Test case 5: Large dataset
        $display("Test case 5: Large dataset");
        arst_i = 1;
        #(CLK_PERIOD);
        arst_i = 0;
        #(CLK_PERIOD);
        exp_max = 0;
        exp_min = {NUM_WIDTH{1'b1}};
        num_sets = 1000;
        for (integer i = 0; i < num_sets; i = i + 1) begin
            data_in_local = $random;
            n0 = data_in_local[7:0];
            n1 = data_in_local[15:8];
            n2 = data_in_local[23:16];
            n3 = data_in_local[31:24];
            temp_max = max_of_four(n0, n1, n2, n3);
            temp_min = min_of_four(n0, n1, n2, n3);
            new_exp_max = (exp_max > temp_max) ? exp_max : temp_max;
            new_exp_min = (exp_min < temp_min) ? exp_min : temp_min;
            data_in = data_in_local;
            start = 1;
            #(CLK_PERIOD);
            start = 0;
            wait(done == 1);
            #(CLK_PERIOD);
            if (data_out[15:8] !== new_exp_max || data_out[7:0] !== new_exp_min)
                $display("Fail: set %d, expected max=%d, min=%d, got max=%d, min=%d", i, new_exp_max, new_exp_min, data_out[15:8], data_out[7:0]);
            else if (i % 100 == 0) $display("Pass: set %d", i);
            exp_max = new_exp_max;
            exp_min = new_exp_min;
        end
        $display("Large dataset completed");

        // Test case 6: Prolonged start signal
        $display("Test case 6: Prolonged start signal");
        arst_i = 1;
        #(CLK_PERIOD);
        arst_i = 0;
        #(CLK_PERIOD);
        exp_max = 0;
        exp_min = {NUM_WIDTH{1'b1}};
        data_in_local = 32'h01020304;
        n0 = data_in_local[7:0];
        n1 = data_in_local[15:8];
        n2 = data_in_local[23:16];
        n3 = data_in_local[31:24];
        temp_max = max_of_four(n0, n1, n2, n3);
        temp_min = min_of_four(n0, n1, n2, n3);
        new_exp_max = (exp_max > temp_max) ? exp_max : temp_max;
        new_exp_min = (exp_min < temp_min) ? exp_min : temp_min;
        data_in = data_in_local;
        start = 1;
        #(CLK_PERIOD); // first cycle
        // keep start high for extra cycles
        repeat (3) #(CLK_PERIOD);
        start = 0;
        wait(done == 1);
        #(CLK_PERIOD);
        if (data_out[15:8] !== new_exp_max || data_out[7:0] !== new_exp_min)
            $display("Fail: prolonged start");
        else $display("Pass: prolonged start");

        $display("All tests completed");
        $finish;
    end
endmodule

src/scripts/wave_max_min.vcd
$date
	Mon Jun 16 16:30:00 2025
$end
$version
	Icarus Verilog
$end
$timescale
	1ps
$end
$scope module accelerator_max_min_tb $end
$var wire 1 ! done $end
$var wire 32 " data_out [31:0] $end
$var parameter 32 # CLK_PERIOD $end
$var parameter 32 $ NUM_WIDTH $end
$var reg 1 % arst_i $end
$var reg 1 & clk_i $end
$var reg 32 ' data_in [31:0] $end
$var reg 32 ( data_in_local [31:0] $end
$var reg 8 ) exp_max [7:0] $end
$var reg 8 * exp_min [7:0] $end
$var reg 8 + n0 [7:0] $end
$var reg 8 , n1 [7:0] $end
$var reg 8 - n2 [7:0] $end
$var reg 8 . n3 [7:0] $end
$var reg 8 / new_exp_max [7:0] $end
$var reg 8 0 new_exp_min [7:0] $end
$var reg 1 1 start $end
$var reg 8 2 temp_max [7:0] $end
$var reg 8 3 temp_min [7:0] $end
$var integer 32 4 num_sets [31:0] $end
$scope function max_of_four $end
$var reg 8 5 a [7:0] $end
$var reg 8 6 b [7:0] $end
$var reg 8 7 c [7:0] $end
$var reg 8 8 d [7:0] $end
$upscope $end
$scope function min_of_four $end
$var reg 8 9 a [7:0] $end
$var reg 8 : b [7:0] $end
$var reg 8 ; c [7:0] $end
$var reg 8 < d [7:0] $end
$upscope $end
$scope module dut $end
$var wire 1 % arst_i $end
$var wire 1 & clk_i $end
$var wire 32 = data_in [31:0] $end
$var wire 1 1 start $end
$var wire 8 > num3 [7:0] $end
$var wire 8 ? num2 [7:0] $end
$var wire 8 @ num1 [7:0] $end
$var wire 8 A num0 [7:0] $end
$var wire 8 B new_min [7:0] $end
$var wire 8 C new_max [7:0] $end
$var wire 8 D min_temp2 [7:0] $end
$var wire 8 E min_temp1 [7:0] $end
$var wire 8 F min_of_four [7:0] $end
$var wire 8 G max_temp2 [7:0] $end
$var wire 8 H max_temp1 [7:0] $end
$var wire 8 I max_of_four [7:0] $end
$var parameter 2 J DONE $end
$var parameter 2 K IDLE $end
$var parameter 32 L NUM_WIDTH $end
$var reg 8 M current_max [7:0] $end
$var reg 8 N current_min [7:0] $end
$var reg 32 O data_out [31:0] $end
$var reg 1 ! done $end
$var reg 2 P state [1:0] $end
$upscope $end
$scope begin $ivl_for_loop0 $end
$var integer 32 Q i [31:0] $end
$upscope $end
$scope begin $ivl_for_loop1 $end
$var integer 32 R i [31:0] $end
$upscope $end
$upscope $end
$enddefinitions $end
$comment Show the parameter values. $end
$dumpall
b1000 L
b0 K
b1 J
b1000 $
b1010 #
$end
#0
$dumpvars
bx R
bx Q
b0 P
b0 O
b11111111 N
b0 M
b0 I
b0 H
b0 G
b0 F
b0 E
b0 D
b0 C
b0 B
b0 A
b0 @
b0 ?
b0 >
b0 =
bx <
bx ;
bx :
bx 9
bx 8
bx 7
bx 6
bx 5
bx 4
bx 3
bx 2
01
bx 0
bx /
bx .
bx -
bx ,
bx +
bx *
bx )
bx (
b0 '
0&
1%
b0 "
0!
$end
#5000
1&
#10000
0&
#15000
1&
#20000
0&
0%
#25000
1&
#30000
b100 C
b1 B
b100 I
b1 F
b100 H
b11 E
b10 G
b1 D
b100 A
b11 @
b10 ?
b1 >
0&
11
b1000000100000001100000100 '
b1000000100000001100000100 =
b1 0
b100 /
b1 3
b100 9
b11 :
b10 ;
b1 <
b100 2
b100 5
b11 6
b10 7
b1 8
b1 .
b10 -
b11 ,
b100 +
b1000000100000001100000100 (
b0 Q
b11111111 *
b0 )
#35000
1!
b1 P
b10000000001 "
b10000000001 O
b1 N
b100 M
1&
#40000
0&
01
#45000
0!
b0 P
1&
#50000
b1000 C
b1000 I
b101 F
b1000 H
b111 E
b110 G
b101 D
b1000 A
b111 @
b110 ?
b101 >
0&
11
b101000001100000011100001000 '
b101000001100000011100001000 =
b1000 /
b101 3
b1000 9
b111 :
b110 ;
b101 <
b1000 2
b1000 5
b111 6
b110 7
b101 8
b101 .
b110 -
b111 ,
b1000 +
b101000001100000011100001000 (
b1 Q
b1 *
b100 )
#55000
1!
b1 P
b100000000001 "
b100000000001 O
b1000 M
1&
#60000
0&
01
#65000
0!
b0 P
1&
#70000
b1100 C
b1100 I
b1001 F
b1100 H
b1011 E
b1010 G
b1001 D
b1100 A
b1011 @
b1010 ?
b1001 >
0&
11
b1001000010100000101100001100 '
b1001000010100000101100001100 =
b1100 /
b1001 3
b1100 9
b1011 :
b1010 ;
b1001 <
b1100 2
b1100 5
b1011 6
b1010 7
b1001 8
b1001 .
b1010 -
b1011 ,
b1100 +
b1001000010100000101100001100 (
b10 Q
b1000 )
#75000
1!
b1 P
b110000000001 "
b110000000001 O
b1100 M
1&
#80000
0&
01
#85000
0!
b0 P
1&
#90000
b1001 B
b0 "
b0 O
b11111111 N
b0 M
0&
1%
b11 Q
b1100 )
#95000
1&
#100000
0&
0%
#105000
1&
#110000
b0 C
b0 B
b0 I
b0 F
b0 H
b0 E
b0 G
b0 D
b0 A
b0 @
b0 ?
b0 >
0&
11
b0 '
b0 =
b0 0
b0 /
b0 3
b0 9
b0 :
b0 ;
b0 <
b0 2
b0 5
b0 6
b0 7
b0 8
b0 .
b0 -
b0 ,
b0 +
b0 (
b11111111 *
b0 )
#115000
1!
b1 P
b0 N
1&
#120000
0&
01
#125000
0!
b0 P
1&
#130000
b11111111 N
0&
1%
#135000
1&
#140000
0&
0%
#145000
1&
#150000
b11111111 C
b11111111 B
b11111111 I
b11111111 F
b11111111 H
b11111111 E
b11111111 G
b11111111 D
b11111111 A
b11111111 @
b11111111 ?
b11111111 >
0&
11
b11111111111111111111111111111111 '
b11111111111111111111111111111111 =
b11111111 0
b11111111 /
b11111111 3
b11111111 9
b11111111 :
b11111111 ;
b11111111 <
b11111111 2
b11111111 5
b11111111 6
b11111111 7
b11111111 8
b11111111 .
b11111111 -
b11111111 ,
b11111111 +
b11111111111111111111111111111111 (
#155000
1!
b1 P
b1111111111111111 "
b1111111111111111 O
b11111111 M
1&
#160000
0&
01
#165000
0!
b0 P
1&
#170000
b0 "
b0 O
b0 M
0&
1%
#175000
1&
#180000
0&
0%
#185000
1&
#190000
b100 C
b1 B
b100 I
b1 F
b100 H
b11 E
b10 G
b1 D
b100 A
b11 @
b10 ?
b1 >
0&
11
b1000000100000001100000100 '
b1000000100000001100000100 =
b1 0
b100 /
b1 3
b100 9
b11 :
b10 ;
b1 <
b100 2
b100 5
b11 6
b10 7
b1 8
b1 .
b10 -
b11 ,
b100 +
b1000000100000001100000100 (
#195000
1!
b1 P
b10000000001 "
b10000000001 O
b1 N
b100 M
1&
#200000
0&
01
#205000
0!
b0 P
1&
#210000
b0 "
b0 O
b11111111 N
b0 M
0&
1%
#215000
1&
#220000
0&
0%
#225000
1&
#230000
b1000 C
b101 B
b1000 I
b101 F
b1000 H
b111 E
b110 G
b101 D
b1000 A
b111 @
b110 ?
b101 >
0&
11
b101000001100000011100001000 '
b101000001100000011100001000 =
b101 0
b1000 /
b101 3
b1000 9
b111 :
b110 ;
b101 <
b1000 2
b1000 5
b111 6
b110 7
b101 8
b101 .
b110 -
b111 ,
b1000 +
b101000001100000011100001000 (
#235000
1!
b1 P
b100000000101 "
b100000000101 O
b101 N
b1000 M
1&
#240000
0&
01
#245000
0!
b0 P
1&
#250000
b0 "
b0 O
b11111111 N
b0 M
0&
1%
#255000
1&
#260000
0&
0%
#265000
1&
#270000
b110101 C
b10010 B
b110101 I
b10010 F
b110101 H
b100100 E
b10101 G
b10010 D
b100100 A
b110101 @
b10101 ?
b10010 >
0&
11
b10010000101010011010100100100 '
b10010000101010011010100100100 =
b10010 0
b110101 /
b10010 3
b100100 9
b110101 :
b10101 ;
b10010 <
b110101 2
b100100 5
b110101 6
b10101 7
b10010 8
b10010 .
b10101 -
b110101 ,
b100100 +
b10010000101010011010100100100 (
b0 R
b1111101000 4
#275000
1!
b1 P
b11010100010010 "
b11010100010010 O
b10010 N
b110101 M
1&
#280000
0&
01
#285000
0!
b0 P
1&
#290000
b11000000 C
b11000000 I
b1011110 F
b1011110 E
b10000001 H
b11000000 G
b10001001 D
b10000001 A
b1011110 @
b10001001 ?
b11000000 >
0&
11
b11000000100010010101111010000001 '
b11000000100010010101111010000001 =
b11000000 /
b1011110 3
b10000001 9
b1011110 :
b10001001 ;
b11000000 <
b11000000 2
b10000001 5
b1011110 6
b10001001 7
b11000000 8
b11000000 .
b10001001 -
b1011110 ,
b10000001 +
b11000000100010010101111010000001 (
b1 R
b10010 *
b110101 )
#295000
1!
b1 P
b1100000000010010 "
b1100000000010010 O
b11000000 M
1&
#300000
0&
01
#305000
0!
b0 P
1&
#310000
b1001 B
b11010110 C
b1001 F
b11010110 I
b11010110 H
b1001 E
b10000100 G
b10000100 D
b1001 A
b11010110 @
b10000100 ?
b10000100 >
0&
11
b10000100100001001101011000001001 '
b10000100100001001101011000001001 =
b1001 0
b11010110 /
b1001 3
b1001 9
b11010110 :
b10000100 ;
b10000100 <
b11010110 2
b1001 5
b11010110 6
b10000100 7
b10000100 8
b10000100 .
b10000100 -
b11010110 ,
b1001 +
b10000100100001001101011000001001 (
b10 R
b11000000 )
#315000
1!
b1 P
b1101011000001001 "
b1101011000001001 O
b1001 N
b11010110 M
1&
#320000
0&
01
#325000
0!
b0 P
1&
#330000
b11110000 C
b1010110 F
b11110000 I
b1010110 E
b1100011 H
b11110000 G
b10110001 D
b1100011 A
b1010110 @
b11110000 ?
b10110001 >
0&
11
b10110001111100000101011001100011 '
b10110001111100000101011001100011 =
b11110000 /
b1010110 3
b1100011 9
b1010110 :
b11110000 ;
b10110001 <
b11110000 2
b1100011 5
b1010110 6
b11110000 7
b10110001 8
b10110001 .
b11110000 -
b1010110 ,
b1100011 +
b10110001111100000101011001100011 (
b11 R
b1001 *
b11010110 )
#335000
1!
b1 P
b1111000000001001 "
b1111000000001001 O
b11110000 M
1&
#340000
0&
01
#345000
0!
b0 P
1&
#350000
b110 B
b10111001 I
b110 F
b1111011 H
b1101 E
b10111001 G
b110 D
b1101 A
b1111011 @
b10111001 ?
b110 >
0&
11
b110101110010111101100001101 '
b110101110010111101100001101 =
b110 0
b110 3
b1101 9
b1111011 :
b10111001 ;
b110 <
b10111001 2
b1101 5
b1111011 6
b10111001 7
b110 8
b110 .
b10111001 -
b1111011 ,
b1101 +
b110101110010111101100001101 (
b100 R
b11110000 )
#355000
1!
b1 P
b1111000000000110 "
b1111000000000110 O
b110 N
1&
#360000
0&
01
#365000
0!
b0 P
1&
#370000
b11011111 I
b1000110 F
b10001101 E
b10011001 H
b11011111 G
b1000110 D
b10001101 A
b10011001 @
b11011111 ?
b1000110 >
0&
11
b1000110110111111001100110001101 '
b1000110110111111001100110001101 =
b1000110 3
b10001101 9
b10011001 :
b11011111 ;
b1000110 <
b11011111 2
b10001101 5
b10011001 6
b11011111 7
b1000110 8
b1000110 .
b11011111 -
b10011001 ,
b10001101 +
b1000110110111111001100110001101 (
b101 R
b110 *
#375000
1!
b1 P
1&
#380000
0&
01
#385000
0!
b0 P
1&
#390000
b11000010 I
b1100101 F
b10000100 H
b1100101 E
b11000010 G
b10110010 D
b1100101 A
b10000100 @
b11000010 ?
b10110010 >
0&
11
b10110010110000101000010001100101 '
b10110010110000101000010001100101 =
b1100101 3
b1100101 9
b10000100 :
b11000010 ;
b10110010 <
b11000010 2
b1100101 5
b10000100 6
b11000010 7
b10110010 8
b10110010 .
b11000010 -
b10000100 ,
b1100101 +
b10110010110000101000010001100101 (
b110 R
#395000
1!
b1 P
1&
#400000
0&
01
#405000
0!
b0 P
1&
#410000
b10001001 I
b10010 F
b1010010 H
b10010 E
b10001001 G
b110111 D
b10010 A
b1010010 @
b110111 ?
b10001001 >
0&
11
b10001001001101110101001000010010 '
b10001001001101110101001000010010 =
b10010 3
b10010 9
b1010010 :
b110111 ;
b10001001 <
b10001001 2
b10010 5
b1010010 6
b110111 7
b10001001 8
b10001001 .
b110111 -
b1010010 ,
b10010 +
b10001001001101110101001000010010 (
b111 R
#415000
1!
b1 P
1&
#420000
0&
01
#425000
0!
b0 P
1&
#430000
b11110011 C
b0 B
b11110011 I
b0 F
b1 E
b11100011 H
b11110011 G
b0 D
b1 A
b11100011 @
b11110011 ?
b0 >
0&
11
b111100111110001100000001 '
b111100111110001100000001 =
b0 0
b11110011 /
b0 3
b1 9
b11100011 :
b11110011 ;
b0 <
b11110011 2
b1 5
b11100011 6
b11110011 7
b0 8
b0 .
b11110011 -
b11100011 ,
b1 +
b111100111110001100000001 (
b1000 R
#435000
1!
b1 P
b1111001100000000 "
b1111001100000000 O
b0 N
b11110011 M
1&
#440000
0&
01
#445000
0!
b0 P
1&
#450000
b11010111 I
b110 F
b1101 E
b11001101 H
b11010111 G
b110 D
b1101 A
b11001101 @
b11010111 ?
b110 >
0&
11
b110110101111100110100001101 '
b110110101111100110100001101 =
b110 3
b1101 9
b11001101 :
b11010111 ;
b110 <
b11010111 2
b1101 5
b11001101 6
b11010111 7
b110 8
b110 .
b11010111 -
b11001101 ,
b1101 +
b110110101111100110100001101 (
b1001 R
b0 *
b11110011 )
#455000
1!
b1 P
1&
#460000
0&
01
#465000
0!
b0 P
1&
#470000
b11110001 I
b100011 F
b1110110 E
b11110001 H
b111011 G
b100011 D
b1110110 A
b11110001 @
b100011 ?
b111011 >
0&
11
b111011001000111111000101110110 '
b111011001000111111000101110110 =
b100011 3
b1110110 9
b11110001 :
b100011 ;
b111011 <
b11110001 2
b1110110 5
b11110001 6
b100011 7
b111011 8
b111011 .
b100011 -
b11110001 ,
b1110110 +
b111011001000111111000101110110 (
b1010 R
#475000
1!
b1 P
1&
#480000
0&
01
#485000
0!
b0 P
1&
#490000
b11001101 I
b11110 F
b111101 E
b11001101 H
b10001101 G
b11110 D
b111101 A
b11001101 @
b10001101 ?
b11110 >
0&
11
b11110100011011100110100111101 '
b11110100011011100110100111101 =
b11110 3
b111101 9
b11001101 :
b10001101 ;
b11110 <
b11001101 2
b111101 5
b11001101 6
b10001101 7
b11110 8
b11110 .
b10001101 -
b11001101 ,
b111101 +
b11110100011011100110100111101 (
b1011 R
#495000
1!
b1 P
1&
#500000
0&
01
#505000
0!
b0 P
1&
#510000
b11101101 I
b1010111 F
b1010111 E
b11101101 H
b11010100 G
b1110110 D
b11101101 A
b1010111 @
b11010100 ?
b1110110 >
0&
11
b1110110110101000101011111101101 '
b1110110110101000101011111101101 =
b1010111 3
b11101101 9
b1010111 :
b11010100 ;
b1110110 <
b11101101 2
b11101101 5
b1010111 6
b11010100 7
b1110110 8
b1110110 .
b11010100 -
b1010111 ,
b11101101 +
b1110110110101000101011111101101 (
b1100 R
#515000
1!
b1 P
1&
#520000
0&
01
#525000
0!
b0 P
1&
#530000
b11110111 C
b11110111 I
b101101 F
b11110111 H
b10001100 E
b1000110 G
b101101 D
b10001100 A
b11110111 @
b101101 ?
b1000110 >
0&
11
b1000110001011011111011110001100 '
b1000110001011011111011110001100 =
b11110111 /
b101101 3
b10001100 9
b11110111 :
b101101 ;
b1000110 <
b11110111 2
b10001100 5
b11110111 6
b101101 7
b1000110 8
b1000110 .
b101101 -
b11110111 ,
b10001100 +
b1000110001011011111011110001100 (
b1101 R
#535000
1!
b1 P
b1111011100000000 "
b1111011100000000 O
b11110111 M
1&
#540000
0&
01
#545000
0!
b0 P
1&
#550000
b11111101 C
b1111100 F
b11111101 I
b11101001 E
b11111001 H
b1111100 D
b11111101 G
b11111001 A
b11101001 @
b11111101 ?
b1111100 >
0&
11
b1111100111111011110100111111001 '
b1111100111111011110100111111001 =
b11111101 /
b1111100 3
b11111001 9
b11101001 :
b11111101 ;
b1111100 <
b11111101 2
b11111001 5
b11101001 6
b11111101 7
b1111100 8
b1111100 .
b11111101 -
b11101001 ,
b11111001 +
b1111100111111011110100111111001 (
b1110 R
b11110111 )
#555000
1!
b1 P
b1111110100000000 "
b1111110100000000 O
b11111101 M
1&
#560000
0&
01
#565000
0!
b0 P
1&
#570000
b11100011 I
b100100 F
b11000110 H
b100100 E
b11100011 G
b110111 D
b11000110 A
b100100 @
b110111 ?
b11100011 >
0&
11
b11100011001101110010010011000110 '
b11100011001101110010010011000110 =
b100100 3
b11000110 9
b100100 :
b110111 ;
b11100011 <
b11100011 2
b11000110 5
b100100 6
b110111 7
b11100011 8
b11100011 .
b110111 -
b100100 ,
b11000110 +
b11100011001101110010010011000110 (
b1111 R
b11111101 )
#575000
1!
b1 P
1&
#580000
0&
01
#585000
0!
b0 P
1&
#590000
b10000100 F
b11110111 I
b11000101 H
b10000100 E
b11100010 D
b11110111 G
b11000101 A
b10000100 @
b11110111 ?
b11100010 >
0&
11
b11100010111101111000010011000101 '
b11100010111101111000010011000101 =
b10000100 3
b11000101 9
b10000100 :
b11110111 ;
b11100010 <
b11110111 2
b11000101 5
b10000100 6
b11110111 7
b11100010 8
b11100010 .
b11110111 -
b10000100 ,
b11000101 +
b11100010111101111000010011000101 (
b10000 R
#595000
1!
b1 P
1&
#600000
0&
01
#605000
0!
b0 P
1&
#610000
b11010101 I
b10011 F
b11010010 H
b10101010 E
b11010101 G
b10011 D
b10101010 A
b11010010 @
b10011 ?
b11010101 >
0&
11
b11010101000100111101001010101010 '
b11010101000100111101001010101010 =
b10011 3
b10101010 9
b11010010 :
b10011 ;
b11010101 <
b11010101 2
b10101010 5
b11010010 6
b10011 7
b11010101 8
b11010101 .
b10011 -
b11010010 ,
b10101010 +
b11010101000100111101001010101010 (
b10001 R
#615000
1!
b1 P
1&
#620000
0&
01
#625000
0!
b0 P
1&
#630000
b1110010 F
b11110111 I
b11100101 E
b11110111 H
b1110010 D
b10101111 G
b11100101 A
b11110111 @
b10101111 ?
b1110010 >
0&
11
b1110010101011111111011111100101 '
b1110010101011111111011111100101 =
b1110010 3
b11100101 9
b11110111 :
b10101111 ;
b1110010 <
b11110111 2
b11100101 5
b11110111 6
b10101111 7
b1110010 8
b1110010 .
b10101111 -
b11110111 ,
b11100101 +
b1110010101011111111011111100101 (
b10010 R
#635000
1!
b1 P
1&
#640000
0&
01
#645000
0!
b0 P
1&
