src/verilog/constants.vh
// `define ADDR_BUS_W 24
`define FE_ADDR_W 22
`define FE_DATA_W 32
`define BE_DATA_W 64
`define BE_ADDR_W 24
`define BE_STRB_W 8
`define FE_STRB_W 4
`define FIFO_DEPTH 16

src/8int-sum_iob-cache/cvc_timing/4num-sum.v
`include "constants.vh"

module accelerator # (
    parameter NUM_WIDTH = `FE_DATA_W / 4
) (
    input  wire                  clk_i,       // Clock
    input  wire                  arst_i,      // Asynchronous reset
    input  wire                  start,       // Start signal
    input  wire [`FE_DATA_W-1:0] data_in,     // 32-bit input
    output reg  [`FE_DATA_W-1:0] data_out,    // 32-bit output
    output reg                   done         // Done signal
);

    // Extract bytes
    wire [NUM_WIDTH-1:0] byte0 = data_in[NUM_WIDTH-1:0];
    wire [NUM_WIDTH-1:0] byte1 = data_in[2*NUM_WIDTH-1:NUM_WIDTH];
    wire [NUM_WIDTH-1:0] byte2 = data_in[3*NUM_WIDTH-1:2*NUM_WIDTH];
    wire [NUM_WIDTH-1:0] byte3 = data_in[4*NUM_WIDTH-1:3*NUM_WIDTH];

    // Compute sum
    wire [NUM_WIDTH+1:0] sum = byte0 + byte1 + byte2 + byte3;

    // State machine
    reg state; // 0: idle, 1: processing
    localparam IDLE = 0, DONE = 1;

    always @(posedge clk_i or posedge arst_i) begin
        if (arst_i) begin
            state <= IDLE;
            data_out <= 0;
            done <= 0;
        end else begin
            case (state)
                IDLE: begin
                    done <= 0;
                    if (start) begin
                        state <= DONE;
                        data_out <= {{(`FE_DATA_W-NUM_WIDTH-2){1'b0}}, sum};
                    end
                end
                DONE: begin
                    done <= 1;
                    if (!start) begin
                        state <= IDLE;
                    end
                end
                default: begin
                    state <= IDLE;
                    done <= 0;
                end
            endcase
        end
    end
endmodule

src/verilog/fifo.v
`include "constants.vh"

module fifo (
  input clk, rst_n,
  input w_en, r_en,
  input [`FE_DATA_W-1:0] data_in,
  output reg [`FE_DATA_W-1:0] data_out,
  output full, empty
);

  parameter PTR_WIDTH = $clog2(`FIFO_DEPTH);   // log2(16) = 4

  reg [PTR_WIDTH-1:0] w_ptr, r_ptr;
  reg [`FE_DATA_W-1:0] queue[0:`FIFO_DEPTH-1];

  // Write data to FIFO
  always @(posedge clk or negedge rst_n) begin
    if (!rst_n) begin
      w_ptr <= 0;
    end else if (w_en && !full) begin
      w_ptr <= w_ptr + 1;
    end
  end

  always @(posedge clk) begin
    if (w_en && !full) begin
      queue[w_ptr] <= data_in;
    end
  end

  // Read data from FIFO
  always @(posedge clk or negedge rst_n) begin
    if (!rst_n) begin
      r_ptr <= 0;
    end else if (r_en && !empty) begin
      r_ptr <= r_ptr + 1;
    end
  end

  always @(posedge clk or negedge rst_n) begin
    if (!rst_n) begin
      data_out <= 0;
    end else if (r_en && !empty) begin
      data_out <= queue[r_ptr];
    end
  end

  // Full and empty logic with wrap-around
  wire [PTR_WIDTH-1:0] w_ptr_next = w_ptr + 1;
  wire [PTR_WIDTH-1:0] r_ptr_next = r_ptr + 1;
  assign full = (w_ptr_next == r_ptr) && (w_en != r_en); // Prevent false full on simultaneous wr/rd
  assign empty = (w_ptr == r_ptr);

endmodule

src/8int-sum_iob-cache/load_store_unit.v
`include "constants.vh"

module load_store_unit (
    input clk,
    input reset,
    input start,
    output reg done,

    // Configuration inputs
    input [`FE_ADDR_W-1:0] load_base_addr,
    input [`FE_ADDR_W-1:0] store_base_addr,
    input [`FE_ADDR_W-1:0] count,

    // Memory interface
    output reg load_req,
    output reg [`FE_ADDR_W-1:0] load_addr,
    input [`FE_DATA_W-1:0] load_data,
    input load_complete,
    output reg store_req,
    output reg [`FE_ADDR_W-1:0] store_addr,
    output reg [`FE_DATA_W-1:0] store_data,
    input store_complete,

    // Accelerator interface
    output reg accelerator_start,
    input accelerator_done,
    input [`FE_DATA_W-1:0] accelerator_data_out,
    output [`FE_DATA_W-1:0] accelerator_data_in
);

    // FIFO signals
    reg load_fifo_write_en;
    reg [`FE_DATA_W-1:0] load_fifo_data_in;
    wire load_fifo_full;
    wire load_fifo_empty;
    reg load_fifo_read_en;
    wire [`FE_DATA_W-1:0] load_fifo_data_out;

    reg store_fifo_write_en;
    reg [`FE_DATA_W-1:0] store_fifo_data_in;
    wire store_fifo_full;
    wire store_fifo_empty;
    reg store_fifo_read_en;
    wire [`FE_DATA_W-1:0] store_fifo_data_out;

    // Instantiate load and store FIFOs
    fifo load_fifo (
        .clk(clk),
        .rst_n(~reset),
        .w_en(load_fifo_write_en),
        .data_in(load_fifo_data_in),
        .r_en(load_fifo_read_en),
        .data_out(load_fifo_data_out),
        .empty(load_fifo_empty),
        .full(load_fifo_full)
    );

    fifo store_fifo (
        .clk(clk),
        .rst_n(~reset),
        .w_en(store_fifo_write_en),
        .data_in(store_fifo_data_in),
        .r_en(store_fifo_read_en),
        .data_out(store_fifo_data_out),
        .empty(store_fifo_empty),
        .full(store_fifo_full)
    );

    // Loader state machine states
    parameter LOADER_IDLE      = 3'd0;
    parameter LOADER_LOAD_REQ  = 3'd1;
    parameter LOADER_LOAD_WAIT = 3'd2;

    // Storer state machine states
    parameter STORER_IDLE      = 3'd0;
    parameter STORER_START     = 3'd1; // New state for starting the storer
    parameter STORER_DEQUEUE   = 3'd2;
    parameter STORER_STORE_REQ = 3'd3;
    parameter STORER_STORE_WAIT= 3'd4;

    reg [2:0] loader_state, storer_state, acc_state;
    reg [`FE_ADDR_W:0] load_counter, store_counter;
    reg [`FE_ADDR_W-1:0] current_load_addr, current_store_addr;

    // Loader state machine
    always @(posedge clk or posedge reset) begin
        if (reset) begin
            loader_state <= LOADER_IDLE;
            load_req <= 0;
            load_counter <= 0;
            current_load_addr <= 0;
            load_fifo_write_en <= 0;
        end else begin
            case (loader_state)
                LOADER_IDLE: begin
                    if (start) begin
                        current_load_addr <= load_base_addr;
                        load_counter <= 0;
                        loader_state <= LOADER_LOAD_REQ;
                    end
                    load_fifo_write_en <= 0;
                end
                LOADER_LOAD_REQ: begin
                    load_fifo_write_en <= 0;
                    if (!load_fifo_full) begin
                        $display("In LOADER_LOAD_REQ");
                        load_req <= 1;
                        load_addr <= current_load_addr;
                        loader_state <= LOADER_LOAD_WAIT;
                    end
                end
                LOADER_LOAD_WAIT: begin
                    load_req <= 0;
                    $display("In LOADER_LOAD_WAIT, load_complete = %b", load_fifo_write_en);
                    if (load_complete) begin
                        load_fifo_data_in <= load_data;
                        load_fifo_write_en <= 1;
                        if (load_counter < count - 22'b1) begin
                            current_load_addr <= current_load_addr + 1;
                            load_counter <= load_counter + 1;
                            loader_state <= LOADER_LOAD_REQ;
                        end else begin
                            loader_state <= LOADER_IDLE;
                        end
                    end else begin
                        load_fifo_write_en <= 0;
                    end
                end
                default: loader_state <= LOADER_IDLE;
            endcase
        end
    end

    // Storer state machine
    always @(posedge clk or posedge reset) begin
        if (reset) begin
            storer_state <= STORER_IDLE;
            store_req <= 0;
            store_counter <= 0;
            current_store_addr <= 0;
            store_fifo_read_en <= 0;
            done <= 0;
        end
        else begin
            case (storer_state)
                STORER_IDLE: begin
                    if (start) begin
                        current_store_addr <= store_base_addr;
                        store_counter <= 0;
                        $display("Storer started with base address: %h", current_store_addr);
                        storer_state <= STORER_START;
                    end
                    done <= 0;
                end
                STORER_START: begin
                    if (!store_fifo_empty) begin
                        storer_state <= STORER_DEQUEUE;
                    end
                end
                STORER_DEQUEUE: begin
                    store_fifo_read_en <= 1;
                    storer_state <= STORER_STORE_REQ;
                end
                STORER_STORE_REQ: begin
                    store_fifo_read_en <= 0;
                    // store_data <= store_fifo_data_out;
                    store_addr <= current_store_addr;
                    store_req <= 1;
                    storer_state <= STORER_STORE_WAIT;
                end
                STORER_STORE_WAIT: begin
                    if (store_complete) begin
                        $display("In STORER_STORE_WAIT, store_complete = %b", store_complete);
                        store_req <= 0;
                        current_store_addr <= current_store_addr + 1;
                        store_counter <= store_counter + 1;
                        if (store_counter < count - 22'b1) begin
                            storer_state <= STORER_START;
                        end else begin
                            done <= 1;
                            storer_state <= STORER_IDLE;
                        end
                    end
                end
                default: storer_state <= STORER_IDLE;
            endcase
        end
    end

    // Define state parameters
    localparam IDLE = 2'b00;
    localparam START_DELAY = 2'b01;
    localparam RUNNING = 2'b10;

    always @(posedge clk or posedge reset) begin
        if (reset) begin
            acc_state <= IDLE;
            accelerator_start <= 0;
            load_fifo_read_en <= 0;
            store_fifo_write_en <= 0;
        end else begin
            // Default assignments
            load_fifo_read_en <= 0;
            store_fifo_write_en <= 0;

            case (acc_state)
                IDLE: begin
                    if (!load_fifo_empty && !accelerator_done) begin
                        load_fifo_read_en <= 1;  // Read from FIFO
                        acc_state <= START_DELAY;
                    end
                end
                START_DELAY: begin
                    load_fifo_read_en <= 0;  // Stop reading
                    accelerator_start <= 1;  // Start the accelerator
                    acc_state <= RUNNING;
                end
                RUNNING: begin
                    if (accelerator_done) begin
                        store_fifo_write_en <= 1;  // Write to store FIFO
                        accelerator_start <= 0;    // Stop the accelerator
                        acc_state <= IDLE;
                    end
                end
                default: acc_state <= IDLE;
            endcase
        end
    end

    // Connect load FIFO output to accelerator input
    assign accelerator_data_in = load_fifo_data_out;
    assign store_fifo_data_in = accelerator_data_out;
    assign store_data = store_fifo_data_out;

endmodule

src/8int-sum_iob-cache/lsu_wrapper.v
`include "constants.vh"

module lsu_wrapper (
    input clk,
    input reset,
    input start,
    output done,
    input [`FE_ADDR_W-1:0] load_base_addr,
    input [`FE_ADDR_W-1:0] store_base_addr,
    input [`FE_ADDR_W-1:0] count,
    output load_req,
    output [`FE_ADDR_W-1:0] load_addr,
    input [`FE_DATA_W-1:0] load_data,
    input load_complete,
    output store_req,
    output [`FE_ADDR_W-1:0] store_addr,
    output [`FE_DATA_W-1:0] store_data,
    input store_complete
);

    // Internal wires for accelerator interface
    wire accelerator_start;
    wire accelerator_done;
    wire [`FE_DATA_W-1:0] accelerator_data_in;
    wire [`FE_DATA_W-1:0] accelerator_data_out;

    // Instantiate load_store_unit
    load_store_unit lsu (
        .clk(clk),
        .reset(reset),
        .start(start),
        .done(done),
        .load_base_addr(load_base_addr),
        .store_base_addr(store_base_addr),
        .count(count),
        .load_req(load_req),
        .load_addr(load_addr),
        .load_data(load_data),
        .load_complete(load_complete),
        .store_req(store_req),
        .store_addr(store_addr),
        .store_data(store_data),
        .store_complete(store_complete),
        .accelerator_start(accelerator_start),
        .accelerator_done(accelerator_done),
        .accelerator_data_in(accelerator_data_in),
        .accelerator_data_out(accelerator_data_out)
    );

    // Instantiate accelerator
    accelerator acc (
        .clk_i(clk),
        .arst_i(reset),
        .start(accelerator_start),
        .data_in(accelerator_data_in),
        .data_out(accelerator_data_out),
        .done(accelerator_done)
    );

endmodule

src/8int-sum_iob-cache/lsu_wrapper_tb.v
`include "constants.vh"
`timescale 1ns / 1ps

module lsu_wrapper_tb;

    // Testbench parameters
    parameter CLK_PERIOD = 10; // 10ns clock period (100MHz)
    parameter DATA_WIDTH = `FE_DATA_W;
    parameter ADDR_WIDTH = `FE_ADDR_W;
    parameter FIFO_DEPTH = `FIFO_DEPTH;

    // Testbench signals
    reg clk;
    reg reset;
    reg start;
    wire done;

    // Configuration inputs
    reg [ADDR_WIDTH-1:0] load_base_addr;
    reg [ADDR_WIDTH-1:0] store_base_addr;
    reg [ADDR_WIDTH-1:0] count;

    // Memory interface
    wire load_req;
    wire [ADDR_WIDTH-1:0] load_addr;
    reg [DATA_WIDTH-1:0] load_data;
    reg load_complete;
    wire store_req;
    wire [ADDR_WIDTH-1:0] store_addr;
    wire [DATA_WIDTH-1:0] store_data;
    reg store_complete;

    // Variables for verification
    reg [7:0] byte0;
    reg [7:0] byte1;
    reg [7:0] byte2;
    reg [7:0] byte3;
    reg [9:0] sum;
    reg [31:0] expected;

    // Instantiate the system_wrapper
    lsu_wrapper dut (
        .clk(clk),
        .reset(reset),
        .start(start),
        .done(done),
        .load_base_addr(load_base_addr),
        .store_base_addr(store_base_addr),
        .count(count),
        .load_req(load_req),
        .load_addr(load_addr),
        .load_data(load_data),
        .load_complete(load_complete),
        .store_req(store_req),
        .store_addr(store_addr),
        .store_data(store_data),
        .store_complete(store_complete)
    );

    // Clock generation
    always #(CLK_PERIOD/2) clk = ~clk;

    // Memory response simulation
    reg [DATA_WIDTH-1:0] memory [0:10000]; // Small memory array for testing
    integer i;

    initial begin
        $dumpfile("lsu_wrapper_tb.vcd");
        $dumpvars(0, lsu_wrapper_tb);
    end
    
    always @(posedge clk) begin
        if (load_req) begin
            $display("Requested load from address 0x%h at time %t", load_addr, $time);
            load_data <= memory[load_addr[3:0]];
            load_complete <= 1;
            #(CLK_PERIOD);
            load_complete <= 0;
        end else begin
            load_complete <= 0;
        end
    end

    always @(posedge clk) begin
        if (store_req) begin
            $display("Stored data at address 0x%h: 0x%h (at time %t)", 
                     store_addr, store_data, $time);
            memory[store_addr[5:0]] <= store_data;
            store_complete <= 1;
        end else begin
            store_complete <= 0;
        end
    end

    // Test procedure
    initial begin
        // Initialize signals
        clk = 0;
        reset = 1;
        start = 0;
        load_base_addr = 22'h000000;
        store_base_addr = 22'h000010;
        count = 4;
        load_data = 0;
        load_complete = 0;
        store_complete = 0;

        // Initialize memory with test data
        memory[0] = 32'h01020000; // Sum = 0x03
        memory[1] = 32'h01010101; // Sum = 0x04
        memory[2] = 32'hFFFFFFFF; // Sum = 0xFF
        memory[3] = 32'h80808080; // Sum = 0x00 (overflow)
        memory[16] = 32'h00000000;
        memory[17] = 32'h00000000;
        memory[18] = 32'h00000000;
        memory[19] = 32'h00000000;

        // Reset sequence
        #(2*CLK_PERIOD);
        reset = 0;
        #(2*CLK_PERIOD);

        // Start the operation
        $display("Starting operation...");
        start = 1;
        #(CLK_PERIOD);
        start = 0;

        // Wait for completion
        wait (done);
        $display("Operation completed at time %t", $time);

        // Verify stored data
        $display("Verifying stored data...");
        for (i = 0; i < count; i = i + 1) begin
            byte0 = memory[i][7:0];
            byte1 = memory[i][15:8];
            byte2 = memory[i][23:16];
            byte3 = memory[i][31:24];
            sum = byte0 + byte1 + byte2 + byte3;
            expected = {22'b0, sum[9:0]}; // Matches accelerator output
            $display("Checking memory[0x%h]: expected 0x%h, got 0x%h", 
                     store_base_addr[5:0] + i, expected, memory[store_base_addr[5:0] + i]);
            if (memory[store_base_addr[5:0] + i] == expected) begin
                $display("PASS");
            end else begin
                $display("FAIL");
            end
        end

        // End simulation
        #(5*CLK_PERIOD);
        $display("Simulation finished.");
        $finish;
    end

endmodule

src/8int-sum_iob-cache/lsu_wrapper_tb.vcd
$date
	Mon Jun  9 14:38:42 2025
$end
$version
	Icarus Verilog
$end
$timescale
	1ps
$end
$scope module lsu_wrapper_tb $end
$var wire 1 ! store_req $end
$var wire 32 " store_data [31:0] $end
$var wire 22 # store_addr [21:0] $end
$var wire 1 $ load_req $end
$var wire 22 % load_addr [21:0] $end
$var wire 1 & done $end
$var reg 8 ' byte0 [7:0] $end
$var reg 8 ( byte1 [7:0] $end
$var reg 8 ) byte2 [7:0] $end
$var reg 8 * byte3 [7:0] $end
$var reg 1 + clk $end
$var reg 22 , count [21:0] $end
$var reg 32 - expected [31:0] $end
$var reg 22 . load_base_addr [21:0] $end
$var reg 1 / load_complete $end
$var reg 32 0 load_data [31:0] $end
$var reg 1 1 reset $end
$var reg 1 2 start $end
$var reg 22 3 store_base_addr [21:0] $end
$var reg 1 4 store_complete $end
$var reg 10 5 sum [9:0] $end
$var integer 32 6 i [31:0] $end
$scope module dut $end
$var wire 1 + clk $end
$var wire 22 7 count [21:0] $end
$var wire 22 8 load_base_addr [21:0] $end
$var wire 1 / load_complete $end
$var wire 32 9 load_data [31:0] $end
$var wire 1 1 reset $end
$var wire 1 2 start $end
$var wire 22 : store_base_addr [21:0] $end
$var wire 1 4 store_complete $end
$var wire 1 ! store_req $end
$var wire 32 ; store_data [31:0] $end
$var wire 22 < store_addr [21:0] $end
$var wire 1 $ load_req $end
$var wire 22 = load_addr [21:0] $end
$var wire 1 & done $end
$var wire 1 > accelerator_start $end
$var wire 1 ? accelerator_done $end
$var wire 32 @ accelerator_data_out [31:0] $end
$var wire 32 A accelerator_data_in [31:0] $end
$scope module acc $end
$var wire 1 1 arst_i $end
$var wire 1 + clk_i $end
$var wire 10 B sum [9:0] $end
$var wire 1 > start $end
$var wire 32 C data_in [31:0] $end
$var wire 8 D byte3 [7:0] $end
$var wire 8 E byte2 [7:0] $end
$var wire 8 F byte1 [7:0] $end
$var wire 8 G byte0 [7:0] $end
$var reg 32 H data_out [31:0] $end
$var reg 1 ? done $end
$var reg 1 I state $end
$upscope $end
$scope module lsu $end
$var wire 32 J accelerator_data_in [31:0] $end
$var wire 32 K accelerator_data_out [31:0] $end
$var wire 1 ? accelerator_done $end
$var wire 1 + clk $end
$var wire 22 L count [21:0] $end
$var wire 22 M load_base_addr [21:0] $end
$var wire 1 / load_complete $end
$var wire 32 N load_data [31:0] $end
$var wire 1 1 reset $end
$var wire 1 2 start $end
$var wire 22 O store_base_addr [21:0] $end
$var wire 1 4 store_complete $end
$var wire 32 P store_data [31:0] $end
$var wire 32 Q store_fifo_data_in [31:0] $end
$var wire 1 R store_fifo_full $end
$var wire 1 S store_fifo_empty $end
$var wire 32 T store_fifo_data_out [31:0] $end
$var wire 1 U load_fifo_full $end
$var wire 1 V load_fifo_empty $end
$var wire 32 W load_fifo_data_out [31:0] $end
$var reg 3 X acc_state [2:0] $end
$var reg 1 > accelerator_start $end
$var reg 22 Y current_load_addr [21:0] $end
$var reg 22 Z current_store_addr [21:0] $end
$var reg 1 & done $end
$var reg 22 [ load_addr [21:0] $end
$var reg 23 \ load_counter [22:0] $end
$var reg 32 ] load_fifo_data_in [31:0] $end
$var reg 1 ^ load_fifo_read_en $end
$var reg 1 _ load_fifo_write_en $end
$var reg 1 $ load_req $end
$var reg 3 ` loader_state [2:0] $end
$var reg 22 a store_addr [21:0] $end
$var reg 23 b store_counter [22:0] $end
$var reg 1 c store_fifo_read_en $end
$var reg 1 d store_fifo_write_en $end
$var reg 1 ! store_req $end
$var reg 3 e storer_state [2:0] $end
$scope module load_fifo $end
$var wire 1 + clk $end
$var wire 32 f data_in [31:0] $end
$var wire 1 U full $end
$var wire 1 ^ r_en $end
$var wire 1 g rst_n $end
$var wire 1 _ w_en $end
$var wire 4 h w_ptr_next [3:0] $end
$var wire 4 i r_ptr_next [3:0] $end
$var wire 1 V empty $end
$var reg 32 j data_out [31:0] $end
$var reg 4 k r_ptr [3:0] $end
$var reg 4 l w_ptr [3:0] $end
$upscope $end
$scope module store_fifo $end
$var wire 1 + clk $end
$var wire 32 m data_in [31:0] $end
$var wire 1 R full $end
$var wire 1 c r_en $end
$var wire 1 n rst_n $end
$var wire 1 d w_en $end
$var wire 4 o w_ptr_next [3:0] $end
$var wire 4 p r_ptr_next [3:0] $end
$var wire 1 S empty $end
$var reg 32 q data_out [31:0] $end
$var reg 4 r r_ptr [3:0] $end
$var reg 4 s w_ptr [3:0] $end
$upscope $end
$upscope $end
$upscope $end
$upscope $end
$enddefinitions $end
#0
$dumpvars
b0 s
b0 r
b0 q
b1 p
b1 o
0n
b0 m
b0 l
b0 k
b0 j
b1 i
b1 h
0g
bx f
b0 e
0d
0c
b0 b
bx a
b0 `
0_
0^
bx ]
b0 \
bx [
b0 Z
b0 Y
b0 X
b0 W
1V
0U
b0 T
1S
0R
b0 Q
b0 P
b10000 O
b0 N
b0 M
b100 L
b0 K
b0 J
0I
b0 H
b0 G
b0 F
b0 E
b0 D
b0 C
b0 B
b0 A
b0 @
0?
0>
bx =
bx <
b0 ;
b10000 :
b0 9
b0 8
b100 7
bx 6
bx 5
04
b10000 3
02
11
b0 0
0/
b0 .
bx -
b100 ,
0+
bx *
bx )
bx (
bx '
0&
bx %
0$
bx #
b0 "
0!
$end
#5000
1+
#10000
0+
#15000
1+
#20000
1g
1n
0+
01
#25000
1+
#30000
0+
#35000
1+
#40000
0+
12
#45000
b1 e
b10000 Z
b1 `
1+
#50000
0+
02
#55000
b10 `
b0 %
b0 =
b0 [
1$
1+
#60000
0+
#65000
0$
1/
b1000000100000000000000000 0
b1000000100000000000000000 9
b1000000100000000000000000 N
1+
#70000
0+
#75000
b1 `
b1 \
b1 Y
1_
b1000000100000000000000000 ]
b1000000100000000000000000 f
0/
1+
#80000
0+
#85000
b10 `
b1 %
b1 =
b1 [
1$
0_
b10 h
0V
b1 l
1+
#90000
0+
#95000
0$
b1 X
1^
1/
b1000000010000000100000001 0
b1000000010000000100000001 9
b1000000010000000100000001 N
1+
#100000
0+
#105000
b1 D
b11 B
b10 E
b10 X
1>
0^
b1 `
b10 \
b10 Y
1_
b1000000010000000100000001 ]
b1000000010000000100000001 f
b1000000100000000000000000 A
b1000000100000000000000000 C
b1000000100000000000000000 J
b1000000100000000000000000 W
b1000000100000000000000000 j
b10 i
1V
b1 k
0/
1+
#110000
0+
#115000
b10 `
b10 %
b10 =
b10 [
1$
0_
b11 Q
b11 m
b11 @
b11 H
b11 K
1I
b11 h
0V
b10 l
1+
#120000
0+
#125000
1?
0$
1/
b11111111111111111111111111111111 0
b11111111111111111111111111111111 9
b11111111111111111111111111111111 N
1+
#130000
0+
#135000
b1 `
b11 \
b11 Y
1_
b11111111111111111111111111111111 ]
b11111111111111111111111111111111 f
b0 X
0>
1d
0/
1+
#140000
0+
#145000
0I
0d
b10 `
b11 %
b11 =
b11 [
1$
0_
b100 h
b11 l
b10 o
0S
b1 s
1+
#150000
0+
#155000
0$
b10 e
0?
1/
b10000000100000001000000010000000 0
b10000000100000001000000010000000 9
b10000000100000001000000010000000 N
1+
#160000
0+
#165000
b1 X
1^
b11 e
1c
b0 `
1_
b10000000100000001000000010000000 ]
b10000000100000001000000010000000 f
0/
1+
#170000
0+
#175000
b1 E
b1 F
b100 B
b1 G
0_
b100 e
1!
b10000 #
b10000 <
b10000 a
0c
b10 X
1>
0^
b101 h
b100 l
b11 i
b10 k
b1000000010000000100000001 A
b1000000010000000100000001 C
b1000000010000000100000001 J
b1000000010000000100000001 W
b1000000010000000100000001 j
b10 p
1S
b1 r
b11 "
b11 ;
b11 P
b11 T
b11 q
1+
#180000
0+
#185000
b100 Q
b100 m
b100 @
b100 H
b100 K
1I
14
1+
#190000
0+
#195000
b1 e
b1 b
b10001 Z
0!
1?
1+
#200000
0+
#205000
b0 X
0>
1d
04
1+
#210000
0+
#215000
0d
0I
b11 o
0S
b10 s
1+
#220000
0+
#225000
0?
b10 e
1+
#230000
0+
#235000
b11 e
1c
b1 X
1^
1+
#240000
0+
#245000
b11111111 D
b11111111 E
b11111111 F
b1111111100 B
b11111111 G
b10 X
1>
0^
b100 e
1!
b10001 #
b10001 <
b10001 a
0c
b11111111111111111111111111111111 A
b11111111111111111111111111111111 C
b11111111111111111111111111111111 J
b11111111111111111111111111111111 W
b11111111111111111111111111111111 j
b100 i
b11 k
b100 "
b100 ;
b100 P
b100 T
b100 q
b11 p
1S
b10 r
1+
#250000
0+
#255000
b1111111100 Q
b1111111100 m
b1111111100 @
b1111111100 H
b1111111100 K
1I
14
1+
#260000
0+
#265000
1?
b1 e
b10 b
b10010 Z
0!
1+
#270000
0+
#275000
b0 X
0>
1d
04
1+
#280000
0+
#285000
0I
0d
b100 o
0S
b11 s
1+
#290000
0+
#295000
b10 e
0?
1+
#300000
0+
#305000
b1 X
1^
b11 e
1c
1+
#310000
0+
#315000
b10000000 D
b10000000 E
b10000000 F
b1000000000 B
b10000000 G
b100 e
1!
b10010 #
b10010 <
b10010 a
0c
b10 X
1>
0^
b101 i
1V
b100 k
b10000000100000001000000010000000 A
b10000000100000001000000010000000 C
b10000000100000001000000010000000 J
b10000000100000001000000010000000 W
b10000000100000001000000010000000 j
b100 p
1S
b11 r
b1111111100 "
b1111111100 ;
b1111111100 P
b1111111100 T
b1111111100 q
1+
#320000
0+
#325000
b1000000000 Q
b1000000000 m
b1000000000 @
b1000000000 H
b1000000000 K
1I
14
1+
#330000
0+
#335000
b1 e
b11 b
b10011 Z
0!
1?
1+
#340000
0+
#345000
b0 X
0>
1d
04
1+
#350000
0+
#355000
0d
0I
b101 o
0S
b100 s
1+
#360000
0+
#365000
0?
b10 e
1+
#370000
0+
#375000
b11 e
1c
1+
#380000
0+
#385000
b100 e
1!
b10011 #
b10011 <
b10011 a
0c
b1000000000 "
b1000000000 ;
b1000000000 P
b1000000000 T
b1000000000 q
b101 p
1S
b100 r
1+
#390000
0+
#395000
14
1+
#400000
0+
#405000
b1000000000 -
b1000000000 5
b10000000 *
b10000000 )
b10000000 (
b10000000 '
b100 6
b0 e
1&
b100 b
b10100 Z
0!
1+
#410000
0+
#415000
0&
04
1+
