src/verilog/constants.vh
// `define ADDR_BUS_W 24
`define FE_ADDR_W 22
`define FE_DATA_W 32
`define BE_DATA_W 64
`define BE_ADDR_W 24
`define BE_STRB_W 8
`define FE_STRB_W 4
`define FIFO_DEPTH 16

src/8int-sum_iob-cache/cvc_timing/4num-sum.v
`include "constants.vh"

module accelerator # (
    parameter NUM_WIDTH = `FE_DATA_W / 4
) (
    input  wire                  clk_i,       // Clock
    input  wire                  arst_i,      // Asynchronous reset
    input  wire                  start,       // Start signal
    input  wire [`FE_DATA_W-1:0] data_in,     // 32-bit input
    output reg  [`FE_DATA_W-1:0] data_out,    // 32-bit output
    output reg                   done         // Done signal
);

    // Extract bytes
    wire [NUM_WIDTH-1:0] byte0 = data_in[NUM_WIDTH-1:0];
    wire [NUM_WIDTH-1:0] byte1 = data_in[2*NUM_WIDTH-1:NUM_WIDTH];
    wire [NUM_WIDTH-1:0] byte2 = data_in[3*NUM_WIDTH-1:2*NUM_WIDTH];
    wire [NUM_WIDTH-1:0] byte3 = data_in[4*NUM_WIDTH-1:3*NUM_WIDTH];

    // Compute sum
    wire [NUM_WIDTH+1:0] sum = byte0 + byte1 + byte2 + byte3;

    // State machine
    reg state; // 0: idle, 1: processing
    localparam IDLE = 0, DONE = 1;

    always @(posedge clk_i or posedge arst_i) begin
        if (arst_i) begin
            state <= IDLE;
            data_out <= 0;
            done <= 0;
        end else begin
            case (state)
                IDLE: begin
                    done <= 0;
                    if (start) begin
                        state <= DONE;
                        data_out <= {{(`FE_DATA_W-NUM_WIDTH-2){1'b0}}, sum};
                    end
                end
                DONE: begin
                    done <= 1;
                    if (!start) begin
                        state <= IDLE;
                    end
                end
                default: begin
                    state <= IDLE;
                    done <= 0;
                end
            endcase
        end
    end
endmodule

src/8int-sum/4num-sum_tb.v
`timescale 1ns / 1ps

`include "constants.vh"

module accelerator_tb;

    // Parameters
    localparam NUM_WIDTH = `FE_DATA_W / 4; // 8 bits
    localparam CLK_PERIOD = 10; // 10ns clock period

    // Signals
    reg                  clk_i;
    reg                  arst_i;
    reg                  start;
    reg  [`FE_DATA_W-1:0] data_in;
    wire [`FE_DATA_W-1:0] data_out;
    wire                 done;

    // Instantiate the accelerator
    accelerator dut (
        .clk_i(clk_i),
        .arst_i(arst_i),
        .start(start),
        .data_in(data_in),
        .data_out(data_out),
        .done(done)
    );

    // Clock generation
    initial begin
        clk_i = 0;
        forever #(CLK_PERIOD/2) clk_i = ~clk_i;
    end

    initial begin
        
        $dumpfile("wave_acc.vcd"); // Set the VCD file name
        $dumpvars(0, accelerator_tb); // Dump all signals in the testbench
    end

    initial begin
        $display("Annotating SDF file for timing simulation");
        $sdf_annotate("acc.sdf", dut);
    end

    // Test procedure
    initial begin
        // Initialize signals
        arst_i = 1;
        start = 0;
        data_in = 0;
        #20;
        arst_i = 0;
        #10;

        // Test case 1: Small numbers (1 + 2 + 3 + 4 = 10)
        $display("Test Case 1: Small numbers (1 + 2 + 3 + 4 = 10)");
        data_in = {8'd4, 8'd3, 8'd2, 8'd1}; // byte3, byte2, byte1, byte0
        start = 1;
        #CLK_PERIOD;
        start = 0;
        wait(done == 1);
        #CLK_PERIOD;
        if (data_out[9:0] == 10 && data_out[31:10] == 0) begin
            $display("PASS: Sum = %d, data_out = %h", data_out[9:0], data_out);
        end else begin
            $display("FAIL: Expected sum = 10, got %d, data_out = %h", data_out[9:0], data_out);
        end
        #10;

        // Test case 2: Overflow case (255 + 255 + 255 + 255 = 1020)
        $display("Test Case 2: Overflow (255 + 255 + 255 + 255 = 1020)");
        data_in = {8'd255, 8'd255, 8'd255, 8'd255};
        start = 1;
        #CLK_PERIOD;
        start = 0;
        wait(done == 1);
        #CLK_PERIOD;
        if (data_out[9:0] == 1020 && data_out[31:10] == 0) begin
            $display("PASS: Sum = %d, data_out = %h", data_out[9:0], data_out);
        end else begin
            $display("FAIL: Expected sum = 1020, got %d, data_out = %h", data_out[9:0], data_out);
        end
        #10;

        // Test case 3: Zeros (0 + 0 + 0 + 0 = 0)
        $display("Test Case 3: Zeros (0 + 0 + 0 + 0 = 0)");
        data_in = {8'd0, 8'd0, 8'd0, 8'd0};
        start = 1;
        #CLK_PERIOD;
        start = 0;
        wait(done == 1);
        #CLK_PERIOD;
        if (data_out[9:0] == 0 && data_out[31:10] == 0) begin
            $display("PASS: Sum = %d, data_out = %h", data_out[9:0], data_out);
        end else begin
            $display("FAIL: Expected sum = 0, got %d, data_out = %h", data_out[9:0], data_out);
        end
        #10;

        // Test case 4: Mixed values (100 + 50 + 25 + 75 = 250)
        $display("Test Case 4: Mixed (100 + 50 + 25 + 75 = 250)");
        data_in = {8'd75, 8'd25, 8'd50, 8'd100};
        start = 1;
        #CLK_PERIOD;
        start = 0;
        wait(done == 1);
        #CLK_PERIOD;
        if (data_out[9:0] == 250 && data_out[31:10] == 0) begin
            $display("PASS: Sum = %d, data_out = %h", data_out[9:0], data_out);
        end else begin
            $display("FAIL: Expected sum = 250, got %d, data_out = %h", data_out[9:0], data_out);
        end
        #10;

        // End simulation
        $display("All tests completed");
        $finish;
    end

endmodule

src/8int-sum_iob-cache/wave_acc.vcd
$date
	Mon Jun  9 11:12:53 2025
$end
$version
	Icarus Verilog
$end
$timescale
	1ps
$end
$scope module accelerator_tb $end
$var wire 1 ! done $end
$var wire 32 " data_out [31:0] $end
$var reg 1 # arst_i $end
$var reg 1 $ clk_i $end
$var reg 32 % data_in [31:0] $end
$var reg 1 & start $end
$scope module dut $end
$var wire 1 # arst_i $end
$var wire 1 $ clk_i $end
$var wire 32 ' data_in [31:0] $end
$var wire 1 & start $end
$var wire 10 ( sum [9:0] $end
$var wire 8 ) byte3 [7:0] $end
$var wire 8 * byte2 [7:0] $end
$var wire 8 + byte1 [7:0] $end
$var wire 8 , byte0 [7:0] $end
$var reg 32 - data_out [31:0] $end
$var reg 1 ! done $end
$var reg 1 . state $end
$upscope $end
$upscope $end
$enddefinitions $end
#0
$dumpvars
0.
b0 -
b0 ,
b0 +
b0 *
b0 )
b0 (
b0 '
0&
b0 %
0$
1#
b0 "
0!
$end
#5000
1$
#10000
0$
#15000
1$
#20000
0$
0#
#25000
1$
#30000
b1 ,
b10 +
b11 *
b1010 (
b100 )
0$
1&
b100000000110000001000000001 %
b100000000110000001000000001 '
#35000
b1010 "
b1010 -
1.
1$
#40000
0$
0&
#45000
0.
1!
1$
#50000
0$
#55000
0!
1$
#60000
0$
#65000
b1111111100 "
b1111111100 -
1.
b11111111 ,
b11111111 +
b11111111 *
b1111111100 (
b11111111 )
1$
1&
b11111111111111111111111111111111 %
b11111111111111111111111111111111 '
#70000
0$
#75000
0.
1!
1$
0&
#80000
0$
#85000
0!
1$
#90000
0$
#95000
b0 "
b0 -
1.
b0 ,
b0 +
b0 *
b0 (
b0 )
1$
1&
b0 %
b0 '
#100000
0$
#105000
0.
1!
1$
0&
#110000
0$
#115000
0!
1$
#120000
0$
#125000
b11111010 "
b11111010 -
1.
b1100100 ,
b110010 +
b11001 *
b11111010 (
b1001011 )
1$
1&
b1001011000110010011001001100100 %
b1001011000110010011001001100100 '
#130000
0$
#135000
0.
1!
1$
0&
#140000
0$
#145000
0!
1$
