src/verilog/constants.vh
// `define ADDR_BUS_W 24
`define FE_ADDR_W 22
`define FE_DATA_W 32
`define BE_DATA_W 64
`define BE_ADDR_W 24
`define BE_STRB_W 8
`define FE_STRB_W 4
`define FIFO_DEPTH 16

src/verilog/fifo.v
`include "constants.vh"

module fifo (
  input clk, rst_n,
  input w_en, r_en,
  input [`FE_DATA_W-1:0] data_in,
  output reg [`FE_DATA_W-1:0] data_out,
  output full, empty
);

  parameter PTR_WIDTH = $clog2(`FIFO_DEPTH);   // log2(16) = 4

  reg [PTR_WIDTH-1:0] w_ptr, r_ptr;
  reg [`FE_DATA_W-1:0] queue[0:`FIFO_DEPTH-1];

  // Write data to FIFO
  always @(posedge clk or negedge rst_n) begin
    if (!rst_n) begin
      w_ptr <= 0;
    end else if (w_en && !full) begin
      w_ptr <= w_ptr + 1;
    end
  end

  always @(posedge clk) begin
    if (w_en && !full) begin
      queue[w_ptr] <= data_in;
    end
  end

  // Read data from FIFO
  always @(posedge clk or negedge rst_n) begin
    if (!rst_n) begin
      r_ptr <= 0;
    end else if (r_en && !empty) begin
      r_ptr <= r_ptr + 1;
    end
  end

  always @(posedge clk or negedge rst_n) begin
    if (!rst_n) begin
      data_out <= 0;
    end else if (r_en && !empty) begin
      data_out <= queue[r_ptr];
    end
  end

  // Full and empty logic with wrap-around
  wire [PTR_WIDTH-1:0] w_ptr_next = w_ptr + 1;
  wire [PTR_WIDTH-1:0] r_ptr_next = r_ptr + 1;
  assign full = (w_ptr_next == r_ptr) && (w_en != r_en); // Prevent false full on simultaneous wr/rd
  assign empty = (w_ptr == r_ptr);

endmodule

src/verilog/fifo_tb.v
`timescale 1ns/1ps

module sync_fifo_tb;
  parameter DATA_WIDTH = 32;
  
  reg clk, rst_n;
  reg w_en, r_en;
  reg [DATA_WIDTH-1:0] data_in;
  wire [DATA_WIDTH-1:0] data_out;
  wire full, empty;
  
  // Array to hold written data for verification
  reg [DATA_WIDTH-1:0] wdata_array [0:1023];
  integer wr_ptr;
  integer rd_ptr;
  
  // Instantiate the FIFO
  fifo s_fifo (
    .clk(clk),
    .rst_n(rst_n),
    .w_en(w_en),
    .r_en(r_en),
    .data_in(data_in),
    .data_out(data_out),
    .full(full),
    .empty(empty)
  );
  
  // Clock generation: 10 ns period
  initial begin
    clk = 0;
    forever #5 clk = ~clk;
  end
  
  // Reset and initialization
  initial begin
    rst_n = 0;
    w_en = 0;
    r_en = 0;
    data_in = 0;
    wr_ptr = 0;
    rd_ptr = 0;
    #100;
    rst_n = 1;
  end
  
  // Write process with short enable pulse
  initial begin
    wait(rst_n == 1);
    repeat(2) begin
      for (integer i = 0; i < 30; i++) begin
        @(posedge clk);
        if (i % 2 == 0) begin
          if (!full) begin
            data_in = $random;
            wdata_array[wr_ptr] = data_in;
            wr_ptr = wr_ptr + 1;
            w_en = 1;  // Assert w_en
            #5;        // Hold for 2 ns
            w_en = 0;  // Deassert w_en
          end
        end
        @(negedge clk); // Wait until end of clock cycle
      end
      #50; // Delay between rounds
    end
  end
  
  // Read process with short enable pulse
  initial begin
    wait(rst_n == 1);
    repeat(10) @(posedge clk); // Delay before starting reads
    repeat(2) begin
      for (integer i = 0; i < 30; i++) begin
        @(posedge clk);
        if (i % 2 == 0) begin
          if (!empty) begin
            r_en = 1;  // Assert r_en
            #5;        // Hold for 2 ns
            r_en = 0;  // Deassert r_en
            // #1;        // Small delay to ensure data_out is stable
            if (data_out !== wdata_array[rd_ptr]) begin
              $display("Time = %0t: Comparison Failed: expected %h, got %h", $time, wdata_array[rd_ptr], data_out);
            end else begin
              $display("Time = %0t: Comparison Passed: expected %h, got %h", $time, wdata_array[rd_ptr], data_out);
            end
            rd_ptr = rd_ptr + 1;
          end
        end
        @(negedge clk); // Wait until end of clock cycle
      end
      #50; // Delay between rounds
    end
    $finish;
  end
  
  // Waveform dump
  initial begin
    $dumpfile("wave_fifo.vcd");
    $dumpvars;
  end
endmodule

src/8int-sum_iob-cache/wave_fifo.vcd
$date
	Mon Jun  9 14:06:14 2025
$end
$version
	Icarus Verilog
$end
$timescale
	1ps
$end
$scope module sync_fifo_tb $end
$var wire 1 ! full $end
$var wire 1 " empty $end
$var wire 32 # data_out [31:0] $end
$var reg 1 $ clk $end
$var reg 32 % data_in [31:0] $end
$var reg 1 & r_en $end
$var reg 1 ' rst_n $end
$var reg 1 ( w_en $end
$var integer 32 ) rd_ptr [31:0] $end
$var integer 32 * wr_ptr [31:0] $end
$scope module s_fifo $end
$var wire 1 $ clk $end
$var wire 32 + data_in [31:0] $end
$var wire 1 ! full $end
$var wire 1 & r_en $end
$var wire 1 ' rst_n $end
$var wire 1 ( w_en $end
$var wire 4 , w_ptr_next [3:0] $end
$var wire 4 - r_ptr_next [3:0] $end
$var wire 1 " empty $end
$var reg 32 . data_out [31:0] $end
$var reg 4 / r_ptr [3:0] $end
$var reg 4 0 w_ptr [3:0] $end
$upscope $end
$scope begin $ivl_for_loop0 $end
$var integer 32 1 i [31:0] $end
$upscope $end
$scope begin $ivl_for_loop1 $end
$var integer 32 2 i [31:0] $end
$upscope $end
$upscope $end
$enddefinitions $end
#0
$dumpvars
bx 2
bx 1
b0 0
b0 /
b0 .
b1 -
b1 ,
b0 +
b0 *
b0 )
0(
0'
0&
b0 %
0$
b0 #
1"
0!
$end
#5000
1$
#10000
0$
#15000
1$
#20000
0$
#25000
1$
#30000
0$
#35000
1$
#40000
0$
#45000
1$
#50000
0$
#55000
1$
#60000
0$
#65000
1$
#70000
0$
#75000
1$
#80000
0$
#85000
1$
#90000
0$
#95000
1$
#100000
b0 1
0$
1'
#105000
b10 ,
0"
b1 0
1(
b1 *
b10010000101010011010100100100 %
b10010000101010011010100100100 +
1$
#110000
0(
0$
#115000
1$
#120000
b1 1
0$
#125000
1$
#130000
b10 1
0$
#135000
b11 ,
b10 0
1(
b10 *
b11000000100010010101111010000001 %
b11000000100010010101111010000001 +
1$
#140000
0(
0$
#145000
1$
#150000
b11 1
0$
#155000
1$
#160000
b100 1
0$
#165000
b100 ,
b11 0
1(
b11 *
b10000100100001001101011000001001 %
b10000100100001001101011000001001 +
1$
#170000
0(
0$
#175000
1$
#180000
b101 1
0$
#185000
1$
#190000
b110 1
0$
#195000
b101 ,
b100 0
b0 2
1(
b100 *
b10110001111100000101011001100011 %
b10110001111100000101011001100011 +
1$
#200000
0(
0$
#205000
b10010000101010011010100100100 #
b10010000101010011010100100100 .
b10 -
b1 /
1&
1$
#210000
b111 1
b1 )
0&
0$
#215000
1$
#220000
b1 2
b1000 1
0$
#225000
b110 ,
b101 0
1(
b101 *
b110101110010111101100001101 %
b110101110010111101100001101 +
1$
#230000
b10 2
0(
0$
#235000
b11 -
b10 /
b11000000100010010101111010000001 #
b11000000100010010101111010000001 .
1&
1$
#240000
b1001 1
b10 )
0&
0$
#245000
1$
#250000
b11 2
b1010 1
0$
#255000
b111 ,
b110 0
1(
b110 *
b1000110110111111001100110001101 %
b1000110110111111001100110001101 +
1$
#260000
b100 2
0(
0$
#265000
b10000100100001001101011000001001 #
b10000100100001001101011000001001 .
b100 -
b11 /
1&
1$
#270000
b1011 1
b11 )
0&
0$
#275000
1$
#280000
b101 2
b1100 1
0$
#285000
b1000 ,
b111 0
1(
b111 *
b10110010110000101000010001100101 %
b10110010110000101000010001100101 +
1$
#290000
b110 2
0(
0$
#295000
b101 -
b100 /
b10110001111100000101011001100011 #
b10110001111100000101011001100011 .
1&
1$
#300000
b1101 1
b100 )
0&
0$
#305000
1$
#310000
b111 2
b1110 1
0$
#315000
b1001 ,
b1000 0
1(
b1000 *
b10001001001101110101001000010010 %
b10001001001101110101001000010010 +
1$
#320000
b1000 2
0(
0$
#325000
b110101110010111101100001101 #
b110101110010111101100001101 .
b110 -
b101 /
1&
1$
#330000
b1111 1
b101 )
0&
0$
#335000
1$
#340000
b1001 2
b10000 1
0$
#345000
b1010 ,
b1001 0
1(
b1001 *
b111100111110001100000001 %
b111100111110001100000001 +
1$
#350000
b1010 2
0(
0$
#355000
b111 -
b110 /
b1000110110111111001100110001101 #
b1000110110111111001100110001101 .
1&
1$
#360000
b10001 1
b110 )
0&
0$
#365000
1$
#370000
b1011 2
b10010 1
0$
#375000
b1011 ,
b1010 0
1(
b1010 *
b110110101111100110100001101 %
b110110101111100110100001101 +
1$
#380000
b1100 2
0(
0$
#385000
b10110010110000101000010001100101 #
b10110010110000101000010001100101 .
b1000 -
b111 /
1&
1$
#390000
b10011 1
b111 )
0&
0$
#395000
1$
#400000
b1101 2
b10100 1
0$
#405000
b1100 ,
b1011 0
1(
b1011 *
b111011001000111111000101110110 %
b111011001000111111000101110110 +
1$
#410000
b1110 2
0(
0$
#415000
b1001 -
b1000 /
b10001001001101110101001000010010 #
b10001001001101110101001000010010 .
1&
1$
#420000
b10101 1
b1000 )
0&
0$
#425000
1$
#430000
b1111 2
b10110 1
0$
#435000
b1101 ,
b1100 0
1(
b1100 *
b11110100011011100110100111101 %
b11110100011011100110100111101 +
1$
#440000
b10000 2
0(
0$
#445000
b111100111110001100000001 #
b111100111110001100000001 .
b1010 -
b1001 /
1&
1$
#450000
b10111 1
b1001 )
0&
0$
#455000
1$
#460000
b10001 2
b11000 1
0$
#465000
b1110 ,
b1101 0
1(
b1101 *
b1110110110101000101011111101101 %
b1110110110101000101011111101101 +
1$
#470000
b10010 2
0(
0$
#475000
b1011 -
b1010 /
b110110101111100110100001101 #
b110110101111100110100001101 .
1&
1$
#480000
b11001 1
b1010 )
0&
0$
#485000
1$
#490000
b10011 2
b11010 1
0$
#495000
b1111 ,
b1110 0
1(
b1110 *
b1000110001011011111011110001100 %
b1000110001011011111011110001100 +
1$
#500000
b10100 2
0(
0$
#505000
b111011001000111111000101110110 #
b111011001000111111000101110110 .
b1100 -
b1011 /
1&
1$
#510000
b11011 1
b1011 )
0&
0$
#515000
1$
#520000
b10101 2
b11100 1
0$
#525000
b0 ,
b1111 0
1(
b1111 *
b1111100111111011110100111111001 %
b1111100111111011110100111111001 +
1$
#530000
b10110 2
0(
0$
#535000
b1101 -
b1100 /
b11110100011011100110100111101 #
b11110100011011100110100111101 .
1&
1$
#540000
b11101 1
b1100 )
0&
0$
#545000
1$
#550000
b10111 2
b11110 1
0$
#555000
1$
#560000
b11000 2
0$
#565000
b1110110110101000101011111101101 #
b1110110110101000101011111101101 .
b1110 -
b1101 /
1&
1$
#570000
b1101 )
0&
0$
#575000
1$
#580000
b11001 2
0$
#585000
1$
#590000
b11010 2
0$
#595000
b1111 -
b1110 /
b1000110001011011111011110001100 #
b1000110001011011111011110001100 .
1&
1$
#600000
b1110 )
0&
0$
b0 1
#605000
b1 ,
b0 0
1(
b10000 *
b11100011001101110010010011000110 %
b11100011001101110010010011000110 +
1$
#610000
b11011 2
0(
0$
#615000
1$
#620000
b1 1
b11100 2
0$
#625000
b1111100111111011110100111111001 #
b1111100111111011110100111111001 .
b0 -
b1111 /
1&
1$
#630000
b10 1
b1111 )
0&
0$
#635000
b10 ,
b1 0
1(
b10001 *
b11100010111101111000010011000101 %
b11100010111101111000010011000101 +
1$
#640000
b11101 2
0(
0$
#645000
1$
#650000
b11 1
b11110 2
0$
#655000
1$
#660000
b100 1
0$
#665000
b11 ,
b10 0
1(
b10010 *
b11010101000100111101001010101010 %
b11010101000100111101001010101010 +
1$
#670000
0(
0$
#675000
1$
#680000
b101 1
0$
#685000
1$
#690000
b110 1
0$
#695000
b100 ,
b11 0
1(
b10011 *
b1110010101011111111011111100101 %
b1110010101011111111011111100101 +
1$
#700000
0(
0$
b0 2
#705000
b11100011001101110010010011000110 #
b11100011001101110010010011000110 .
b1 -
b0 /
1&
1$
#710000
b111 1
b10000 )
0&
0$
#715000
1$
#720000
b1 2
b1000 1
0$
#725000
b101 ,
b100 0
1(
b10100 *
b10111011110100100111001001110111 %
b10111011110100100111001001110111 +
1$
#730000
b10 2
0(
0$
#735000
b10 -
b1 /
b11100010111101111000010011000101 #
b11100010111101111000010011000101 .
1&
1$
#740000
b1001 1
b10001 )
0&
0$
#745000
1$
#750000
b11 2
b1010 1
0$
#755000
b110 ,
b101 0
1(
b10101 *
b10001001001100101101011000010010 %
b10001001001100101101011000010010 +
1$
#760000
b100 2
0(
0$
#765000
b11010101000100111101001010101010 #
b11010101000100111101001010101010 .
b11 -
b10 /
1&
1$
#770000
b1011 1
b10010 )
0&
0$
#775000
1$
#780000
b101 2
b1100 1
0$
#785000
b111 ,
b110 0
1(
b10110 *
b1000111111011001101101110001111 %
b1000111111011001101101110001111 +
1$
#790000
b110 2
0(
0$
#795000
b100 -
b11 /
b1110010101011111111011111100101 #
b1110010101011111111011111100101 .
1&
1$
#800000
b1101 1
b10011 )
0&
0$
#805000
1$
#810000
b111 2
b1110 1
0$
#815000
b1000 ,
b111 0
1(
b10111 *
b1111001001100000110100111110010 %
b1111001001100000110100111110010 +
1$
#820000
b1000 2
0(
0$
#825000
b10111011110100100111001001110111 #
b10111011110100100111001001110111 .
b101 -
b100 /
1&
1$
#830000
b1111 1
b10100 )
0&
0$
#835000
1$
#840000
b1001 2
b10000 1
0$
#845000
b1001 ,
b1000 0
1(
b11000 *
b11100111011101101001011011001110 %
b11100111011101101001011011001110 +
1$
#850000
b1010 2
0(
0$
#855000
b110 -
b101 /
b10001001001100101101011000010010 #
b10001001001100101101011000010010 .
1&
1$
#860000
b10001 1
b10101 )
0&
0$
#865000
1$
#870000
b1011 2
b10010 1
0$
#875000
b1010 ,
b1001 0
1(
b11001 *
b11110100000000000111101011101000 %
b11110100000000000111101011101000 +
1$
#880000
b1100 2
0(
0$
#885000
b1000111111011001101101110001111 #
b1000111111011001101101110001111 .
b111 -
b110 /
1&
1$
#890000
b10011 1
b10110 )
0&
0$
#895000
1$
#900000
b1101 2
b10100 1
0$
#905000
b1011 ,
b1010 0
1(
b11010 *
b11100010110010100100111011000101 %
b11100010110010100100111011000101 +
1$
#910000
b1110 2
0(
0$
#915000
b1000 -
b111 /
b1111001001100000110100111110010 #
b1111001001100000110100111110010 .
1&
1$
#920000
b10101 1
b10111 )
0&
0$
#925000
1$
#930000
b1111 2
b10110 1
0$
#935000
b1100 ,
b1011 0
1(
b11011 *
b101110010110000100100101011100 %
b101110010110000100100101011100 +
1$
#940000
b10000 2
0(
0$
#945000
b11100111011101101001011011001110 #
b11100111011101101001011011001110 .
b1001 -
b1000 /
1&
1$
#950000
b10111 1
b11000 )
0&
0$
#955000
1$
#960000
b10001 2
b11000 1
0$
#965000
b1101 ,
b1100 0
1(
b11100 *
b11011110100011100010100010111101 %
b11011110100011100010100010111101 +
1$
#970000
b10010 2
0(
0$
#975000
b1010 -
b1001 /
b11110100000000000111101011101000 #
b11110100000000000111101011101000 .
1&
1$
#980000
b11001 1
b11001 )
0&
0$
#985000
1$
#990000
b10011 2
b11010 1
0$
#995000
b1110 ,
b1101 0
1(
b11101 *
b10010110101010110101100000101101 %
b10010110101010110101100000101101 +
1$
#1000000
b10100 2
0(
0$
#1005000
b11100010110010100100111011000101 #
b11100010110010100100111011000101 .
b1011 -
b1010 /
1&
1$
#1010000
b11011 1
b11010 )
0&
0$
#1015000
1$
#1020000
b10101 2
b11100 1
0$
#1025000
b1111 ,
b1110 0
1(
b11110 *
b10110010101001110010011001100101 %
b10110010101001110010011001100101 +
1$
#1030000
b10110 2
0(
0$
#1035000
b1100 -
b1011 /
b101110010110000100100101011100 #
b101110010110000100100101011100 .
1&
1$
#1040000
b11101 1
b11011 )
0&
0$
#1045000
1$
#1050000
b10111 2
b11110 1
0$
#1055000
1$
#1060000
b11000 2
0$
#1065000
b11011110100011100010100010111101 #
b11011110100011100010100010111101 .
b1101 -
b1100 /
1&
1$
#1070000
b11100 )
0&
0$
#1075000
1$
#1080000
b11001 2
0$
#1085000
1$
#1090000
b11010 2
0$
#1095000
b1110 -
b1101 /
b10010110101010110101100000101101 #
b10010110101010110101100000101101 .
1&
1$
#1100000
b11101 )
0&
0$
#1105000
1$
#1110000
b11011 2
0$
#1115000
1$
#1120000
b11100 2
0$
#1125000
b10110010101001110010011001100101 #
b10110010101001110010011001100101 .
b1111 -
1"
b1110 /
1&
1$
#1130000
b11110 )
0&
0$
#1135000
1$
#1140000
b11101 2
0$
#1145000
1$
#1150000
b11110 2
0$
